{
"meta":{"test_sets":[],"test_metrics":[],"learn_metrics":[{"best_value":"Min","name":"MAE"}],"launch_mode":"Train","parameters":"","iteration_count":1001,"learn_sets":["learn"],"name":"experiment"},
"iterations":[
{"learn":[5.311070578],"iteration":0,"passed_time":0.01662104024,"remaining_time":16.62104024},
{"learn":[5.187841278],"iteration":1,"passed_time":0.03504205114,"remaining_time":17.50350454},
{"learn":[5.076360762],"iteration":2,"passed_time":0.05957377881,"remaining_time":19.81821042},
{"learn":[4.971000736],"iteration":3,"passed_time":0.15215544,"remaining_time":37.92474343},
{"learn":[4.871782945],"iteration":4,"passed_time":0.1970202892,"remaining_time":39.24644161},
{"learn":[4.780762912],"iteration":5,"passed_time":0.2372733029,"remaining_time":39.34782273},
{"learn":[4.691379937],"iteration":6,"passed_time":0.2526538857,"remaining_time":35.87685177},
{"learn":[4.6090374],"iteration":7,"passed_time":0.2669712506,"remaining_time":33.13780648},
{"learn":[4.528800763],"iteration":8,"passed_time":0.2811586674,"remaining_time":30.98993312},
{"learn":[4.46053991],"iteration":9,"passed_time":0.2968423477,"remaining_time":29.41707665},
{"learn":[4.391128814],"iteration":10,"passed_time":0.316162447,"remaining_time":28.45462023},
{"learn":[4.329221023],"iteration":11,"passed_time":0.3341665069,"remaining_time":27.54088961},
{"learn":[4.269511143],"iteration":12,"passed_time":0.3492856167,"remaining_time":26.54570687},
{"learn":[4.214173604],"iteration":13,"passed_time":0.3646933275,"remaining_time":25.71087959},
{"learn":[4.1614815],"iteration":14,"passed_time":0.3802932091,"remaining_time":24.99794028},
{"learn":[4.111551365],"iteration":15,"passed_time":0.3952294178,"remaining_time":24.33131103},
{"learn":[4.064903072],"iteration":16,"passed_time":0.4115840774,"remaining_time":23.82345483},
{"learn":[4.023042279],"iteration":17,"passed_time":0.429260575,"remaining_time":23.44239696},
{"learn":[3.983469165],"iteration":18,"passed_time":0.4519443655,"remaining_time":23.35838773},
{"learn":[3.943931019],"iteration":19,"passed_time":0.4722558857,"remaining_time":23.16415119},
{"learn":[3.904913599],"iteration":20,"passed_time":0.4912155051,"remaining_time":22.92339024},
{"learn":[3.872824964],"iteration":21,"passed_time":0.5082307511,"remaining_time":22.61626843},
{"learn":[3.839152754],"iteration":22,"passed_time":0.5261643557,"remaining_time":22.37342347},
{"learn":[3.809079671],"iteration":23,"passed_time":0.5445998424,"remaining_time":22.16975192},
{"learn":[3.779249832],"iteration":24,"passed_time":0.5625419974,"remaining_time":21.96163958},
{"learn":[3.749901101],"iteration":25,"passed_time":0.5799785211,"remaining_time":21.74919454},
{"learn":[3.721899741],"iteration":26,"passed_time":0.5974171992,"remaining_time":21.5512723},
{"learn":[3.695953207],"iteration":27,"passed_time":0.6139673166,"remaining_time":21.33536425},
{"learn":[3.670929908],"iteration":28,"passed_time":0.6285341242,"remaining_time":21.06672995},
{"learn":[3.647639272],"iteration":29,"passed_time":0.6435850211,"remaining_time":20.83070185},
{"learn":[3.62480421],"iteration":30,"passed_time":0.6603091887,"remaining_time":20.66128752},
{"learn":[3.603884055],"iteration":31,"passed_time":0.6757274734,"remaining_time":20.46187255},
{"learn":[3.583232013],"iteration":32,"passed_time":0.6916545266,"remaining_time":20.28853278},
{"learn":[3.564582583],"iteration":33,"passed_time":0.7087051299,"remaining_time":20.15640767},
{"learn":[3.545997633],"iteration":34,"passed_time":0.7241512831,"remaining_time":19.98657541},
{"learn":[3.528593349],"iteration":35,"passed_time":0.7380228415,"remaining_time":19.78311228},
{"learn":[3.510785444],"iteration":36,"passed_time":0.7536539186,"remaining_time":19.63573993},
{"learn":[3.495005384],"iteration":37,"passed_time":0.7676874921,"remaining_time":19.45481723},
{"learn":[3.478785594],"iteration":38,"passed_time":0.7823896242,"remaining_time":19.29894406},
{"learn":[3.46384432],"iteration":39,"passed_time":0.7984446536,"remaining_time":19.1826328},
{"learn":[3.44620198],"iteration":40,"passed_time":0.8224863491,"remaining_time":19.25821696},
{"learn":[3.433400368],"iteration":41,"passed_time":0.8419484377,"remaining_time":19.22448933},
{"learn":[3.419763317],"iteration":42,"passed_time":0.8602774474,"remaining_time":19.16618127},
{"learn":[3.40735785],"iteration":43,"passed_time":0.880396921,"remaining_time":19.14863303},
{"learn":[3.394383163],"iteration":44,"passed_time":0.8978624425,"remaining_time":19.07458878},
{"learn":[3.382583486],"iteration":45,"passed_time":0.9162660933,"remaining_time":19.02248085},
{"learn":[3.373481938],"iteration":46,"passed_time":0.9324412622,"remaining_time":18.92657371},
{"learn":[3.361243258],"iteration":47,"passed_time":0.9559230733,"remaining_time":18.97905602},
{"learn":[3.350442535],"iteration":48,"passed_time":0.978452591,"remaining_time":19.00993605},
{"learn":[3.340027703],"iteration":49,"passed_time":1.003333249,"remaining_time":19.0833984},
{"learn":[3.329552161],"iteration":50,"passed_time":1.022673656,"remaining_time":19.04980339},
{"learn":[3.319331348],"iteration":51,"passed_time":1.037591175,"remaining_time":18.93603895},
{"learn":[3.309834731],"iteration":52,"passed_time":1.052870275,"remaining_time":18.8324721},
{"learn":[3.30104341],"iteration":53,"passed_time":1.068773476,"remaining_time":18.74312003},
{"learn":[3.2929784],"iteration":54,"passed_time":1.08404302,"remaining_time":18.64553994},
{"learn":[3.285281119],"iteration":55,"passed_time":1.101551531,"remaining_time":18.58868209},
{"learn":[3.277317979],"iteration":56,"passed_time":1.115135204,"remaining_time":18.46820408},
{"learn":[3.268879764],"iteration":57,"passed_time":1.130197287,"remaining_time":18.375449},
{"learn":[3.258804481],"iteration":58,"passed_time":1.145269309,"remaining_time":18.28548626},
{"learn":[3.249976628],"iteration":59,"passed_time":1.160523595,"remaining_time":18.20087838},
{"learn":[3.241614889],"iteration":60,"passed_time":1.177245969,"remaining_time":18.14116739},
{"learn":[3.235056331],"iteration":61,"passed_time":1.192948635,"remaining_time":18.06739949},
{"learn":[3.22748376],"iteration":62,"passed_time":1.208040393,"remaining_time":17.98637918},
{"learn":[3.221491413],"iteration":63,"passed_time":1.226106337,"remaining_time":17.95096309},
{"learn":[3.214626031],"iteration":64,"passed_time":1.249235957,"remaining_time":17.98899778},
{"learn":[3.208166507],"iteration":65,"passed_time":1.26644045,"remaining_time":17.94123971},
{"learn":[3.199434871],"iteration":66,"passed_time":1.285431847,"remaining_time":17.91930366},
{"learn":[3.192281337],"iteration":67,"passed_time":1.318971409,"remaining_time":18.0970636},
{"learn":[3.186106941],"iteration":68,"passed_time":1.340197429,"remaining_time":18.10237686},
{"learn":[3.180637705],"iteration":69,"passed_time":1.358828316,"remaining_time":18.0724166},
{"learn":[3.17441896],"iteration":70,"passed_time":1.383132885,"remaining_time":18.11709272},
{"learn":[3.169670674],"iteration":71,"passed_time":1.398849369,"remaining_time":18.04904256},
{"learn":[3.164309467],"iteration":72,"passed_time":1.415969745,"remaining_time":18.00027292},
{"learn":[3.155920822],"iteration":73,"passed_time":1.430514773,"remaining_time":17.92009722},
{"learn":[3.150524902],"iteration":74,"passed_time":1.446396971,"remaining_time":17.85818127},
{"learn":[3.144717919],"iteration":75,"passed_time":1.461040911,"remaining_time":17.78240582},
{"learn":[3.136683482],"iteration":76,"passed_time":1.477115585,"remaining_time":17.72538702},
{"learn":[3.131534944],"iteration":77,"passed_time":1.489869431,"remaining_time":17.6301216},
{"learn":[3.126022977],"iteration":78,"passed_time":1.505382431,"remaining_time":17.56914686},
{"learn":[3.120328875],"iteration":79,"passed_time":1.519981381,"remaining_time":17.49878565},
{"learn":[3.11533581],"iteration":80,"passed_time":1.537346537,"remaining_time":17.46121993},
{"learn":[3.111093876],"iteration":81,"passed_time":1.551949309,"remaining_time":17.39318798},
{"learn":[3.10651835],"iteration":82,"passed_time":1.567008575,"remaining_time":17.33149243},
{"learn":[3.101433386],"iteration":83,"passed_time":1.581867122,"remaining_time":17.26871608},
{"learn":[3.097545031],"iteration":84,"passed_time":1.597284763,"remaining_time":17.21309227},
{"learn":[3.093818724],"iteration":85,"passed_time":1.612325959,"remaining_time":17.15439828},
{"learn":[3.090465646],"iteration":86,"passed_time":1.626731085,"remaining_time":17.09002542},
{"learn":[3.086300597],"iteration":87,"passed_time":1.642772951,"remaining_time":17.04376937},
{"learn":[3.081929959],"iteration":88,"passed_time":1.661288338,"remaining_time":17.02353893},
{"learn":[3.077605271],"iteration":89,"passed_time":1.676832221,"remaining_time":16.97326837},
{"learn":[3.072953963],"iteration":90,"passed_time":1.692034382,"remaining_time":16.92034382},
{"learn":[3.069633896],"iteration":91,"passed_time":1.706646153,"remaining_time":16.86240601},
{"learn":[3.065555435],"iteration":92,"passed_time":1.720998996,"remaining_time":16.80287192},
{"learn":[3.060514431],"iteration":93,"passed_time":1.735199237,"remaining_time":16.74282668},
{"learn":[3.057048565],"iteration":94,"passed_time":1.753544157,"remaining_time":16.72327375},
{"learn":[3.052651397],"iteration":95,"passed_time":1.768401083,"remaining_time":16.67086438},
{"learn":[3.049547777],"iteration":96,"passed_time":1.781954031,"remaining_time":16.60707675},
{"learn":[3.045148726],"iteration":97,"passed_time":1.798305214,"remaining_time":16.57009804},
{"learn":[3.040076938],"iteration":98,"passed_time":1.81415352,"remaining_time":16.52895429},
{"learn":[3.036049849],"iteration":99,"passed_time":1.830132232,"remaining_time":16.48949141},
{"learn":[3.032513136],"iteration":100,"passed_time":1.844659084,"remaining_time":16.43755619},
{"learn":[3.029336008],"iteration":101,"passed_time":1.859655738,"remaining_time":16.39049519},
{"learn":[3.02591493],"iteration":102,"passed_time":1.875465522,"remaining_time":16.351146},
{"learn":[3.02261199],"iteration":103,"passed_time":1.890713139,"remaining_time":16.30740082},
{"learn":[3.019022394],"iteration":104,"passed_time":1.905815887,"remaining_time":16.26296223},
{"learn":[3.015438675],"iteration":105,"passed_time":1.92279931,"remaining_time":16.23495643},
{"learn":[3.013066379],"iteration":106,"passed_time":1.938177691,"remaining_time":16.19374631},
{"learn":[3.009831971],"iteration":107,"passed_time":1.956609762,"remaining_time":16.17826405},
{"learn":[3.005537348],"iteration":108,"passed_time":1.972937704,"remaining_time":16.14550855},
{"learn":[3.001174587],"iteration":109,"passed_time":1.996828887,"remaining_time":16.17431399},
{"learn":[2.997158265],"iteration":110,"passed_time":2.01057641,"remaining_time":16.12083788},
{"learn":[2.99439159],"iteration":111,"passed_time":2.024440399,"remaining_time":16.06899567},
{"learn":[2.990922427],"iteration":112,"passed_time":2.039792281,"remaining_time":16.0295181},
{"learn":[2.988301215],"iteration":113,"passed_time":2.056479471,"remaining_time":16.00085343},
{"learn":[2.984918777],"iteration":114,"passed_time":2.07104397,"remaining_time":15.95604311},
{"learn":[2.981650995],"iteration":115,"passed_time":2.08628187,"remaining_time":15.91689185},
{"learn":[2.979022419],"iteration":116,"passed_time":2.103124844,"remaining_time":15.8902766},
{"learn":[2.974940011],"iteration":117,"passed_time":2.118818936,"remaining_time":15.85522983},
{"learn":[2.971532889],"iteration":118,"passed_time":2.136036823,"remaining_time":15.83180233},
{"learn":[2.967129195],"iteration":119,"passed_time":2.151905475,"remaining_time":15.79857269},
{"learn":[2.963824302],"iteration":120,"passed_time":2.171668421,"remaining_time":15.79395215},
{"learn":[2.961274973],"iteration":121,"passed_time":2.188572906,"remaining_time":15.7684884},
{"learn":[2.958341924],"iteration":122,"passed_time":2.205856594,"remaining_time":15.74587065},
{"learn":[2.955699773],"iteration":123,"passed_time":2.222872703,"remaining_time":15.72144645},
{"learn":[2.953012366],"iteration":124,"passed_time":2.237714345,"remaining_time":15.68190213},
{"learn":[2.950584676],"iteration":125,"passed_time":2.253396394,"remaining_time":15.64858607},
{"learn":[2.948049037],"iteration":126,"passed_time":2.26877505,"remaining_time":15.61345979},
{"learn":[2.945762584],"iteration":127,"passed_time":2.28487605,"remaining_time":15.58356869},
{"learn":[2.942855134],"iteration":128,"passed_time":2.300699542,"remaining_time":15.55201551},
{"learn":[2.939956481],"iteration":129,"passed_time":2.315551802,"remaining_time":15.51419708},
{"learn":[2.937328865],"iteration":130,"passed_time":2.33156597,"remaining_time":15.48444575},
{"learn":[2.934802865],"iteration":131,"passed_time":2.348064328,"remaining_time":15.45809016},
{"learn":[2.931423478],"iteration":132,"passed_time":2.363922373,"remaining_time":15.42770391},
{"learn":[2.929096495],"iteration":133,"passed_time":2.38260921,"remaining_time":15.4158372},
{"learn":[2.924877865],"iteration":134,"passed_time":2.403882117,"remaining_time":15.42045862},
{"learn":[2.921964481],"iteration":135,"passed_time":2.420730527,"remaining_time":15.39655813},
{"learn":[2.919605015],"iteration":136,"passed_time":2.436489022,"remaining_time":15.36588697},
{"learn":[2.917075908],"iteration":137,"passed_time":2.456046425,"remaining_time":15.35918888},
{"learn":[2.914431436],"iteration":138,"passed_time":2.478783553,"remaining_time":15.37202463},
{"learn":[2.911598311],"iteration":139,"passed_time":2.497362211,"remaining_time":15.3587776},
{"learn":[2.90987077],"iteration":140,"passed_time":2.516803987,"remaining_time":15.35071935},
{"learn":[2.907024084],"iteration":141,"passed_time":2.535708322,"remaining_time":15.33924964},
{"learn":[2.903946309],"iteration":142,"passed_time":2.552544519,"remaining_time":15.31526712},
{"learn":[2.900717553],"iteration":143,"passed_time":2.572947255,"remaining_time":15.31260971},
{"learn":[2.896753738],"iteration":144,"passed_time":2.592222779,"remaining_time":15.30305309},
{"learn":[2.894619916],"iteration":145,"passed_time":2.611874008,"remaining_time":15.29556354},
{"learn":[2.892200461],"iteration":146,"passed_time":2.635696321,"remaining_time":15.31214053},
{"learn":[2.889911241],"iteration":147,"passed_time":2.657330643,"remaining_time":15.31556107},
{"learn":[2.88676685],"iteration":148,"passed_time":2.679183299,"remaining_time":15.31989376},
{"learn":[2.883541934],"iteration":149,"passed_time":2.702451311,"remaining_time":15.3319071},
{"learn":[2.880577484],"iteration":150,"passed_time":2.726596501,"remaining_time":15.3483909},
{"learn":[2.877759815],"iteration":151,"passed_time":2.745963961,"remaining_time":15.33765397},
{"learn":[2.875404039],"iteration":152,"passed_time":2.763807878,"remaining_time":15.31836},
{"learn":[2.872381742],"iteration":153,"passed_time":2.783020109,"remaining_time":15.3066106},
{"learn":[2.869478885],"iteration":154,"passed_time":2.802106821,"remaining_time":15.29407981},
{"learn":[2.866946162],"iteration":155,"passed_time":2.821642988,"remaining_time":15.28389952},
{"learn":[2.864278229],"iteration":156,"passed_time":2.842025234,"remaining_time":15.27814839},
{"learn":[2.861228651],"iteration":157,"passed_time":2.861839001,"remaining_time":15.26917898},
{"learn":[2.857804924],"iteration":158,"passed_time":2.883895474,"remaining_time":15.27194962},
{"learn":[2.855721675],"iteration":159,"passed_time":2.902021155,"remaining_time":15.2537487},
{"learn":[2.853397374],"iteration":160,"passed_time":2.919301375,"remaining_time":15.23113761},
{"learn":[2.851108971],"iteration":161,"passed_time":2.936986577,"remaining_time":15.21068974},
{"learn":[2.84794485],"iteration":162,"passed_time":2.95380022,"remaining_time":15.18579499},
{"learn":[2.845541874],"iteration":163,"passed_time":2.970812754,"remaining_time":15.16201387},
{"learn":[2.843578637],"iteration":164,"passed_time":2.987703736,"remaining_time":15.13769893},
{"learn":[2.841725929],"iteration":165,"passed_time":3.002496143,"remaining_time":15.10291735},
{"learn":[2.839338464],"iteration":166,"passed_time":3.021432518,"remaining_time":15.08907018},
{"learn":[2.835961351],"iteration":167,"passed_time":3.03685191,"remaining_time":15.05772405},
{"learn":[2.833760607],"iteration":168,"passed_time":3.058837406,"remaining_time":15.05889185},
{"learn":[2.831882707],"iteration":169,"passed_time":3.108861801,"remaining_time":15.19684798},
{"learn":[2.82970423],"iteration":170,"passed_time":3.140593648,"remaining_time":15.24381712},
{"learn":[2.827771349],"iteration":171,"passed_time":3.181832873,"remaining_time":15.33569449},
{"learn":[2.825062911],"iteration":172,"passed_time":3.207860348,"remaining_time":15.35322756},
{"learn":[2.822787545],"iteration":173,"passed_time":3.23454839,"remaining_time":15.37339953},
{"learn":[2.820792295],"iteration":174,"passed_time":3.265274418,"remaining_time":15.41209525},
{"learn":[2.81765825],"iteration":175,"passed_time":3.293182298,"remaining_time":15.43679202},
{"learn":[2.815673237],"iteration":176,"passed_time":3.318880512,"remaining_time":15.45060758},
{"learn":[2.812460089],"iteration":177,"passed_time":3.344808771,"remaining_time":15.4650428},
{"learn":[2.809961305],"iteration":178,"passed_time":3.36697248,"remaining_time":15.46173955},
{"learn":[2.808249031],"iteration":179,"passed_time":3.389105475,"remaining_time":15.45808664},
{"learn":[2.806432244],"iteration":180,"passed_time":3.41052386,"remaining_time":15.45099207},
{"learn":[2.804326954],"iteration":181,"passed_time":3.433273146,"remaining_time":15.44972916},
{"learn":[2.801871332],"iteration":182,"passed_time":3.458401114,"remaining_time":15.458864},
{"learn":[2.799774218],"iteration":183,"passed_time":3.480794996,"remaining_time":15.45548648},
{"learn":[2.797984295],"iteration":184,"passed_time":3.503850636,"remaining_time":15.45482226},
{"learn":[2.796077878],"iteration":185,"passed_time":3.525494944,"remaining_time":15.44773322},
{"learn":[2.793998395],"iteration":186,"passed_time":3.54692103,"remaining_time":15.4395386},
{"learn":[2.791827262],"iteration":187,"passed_time":3.570140775,"remaining_time":15.43895984},
{"learn":[2.789166723],"iteration":188,"passed_time":3.731242377,"remaining_time":16.0305228},
{"learn":[2.78673732],"iteration":189,"passed_time":3.820871315,"remaining_time":16.30908756},
{"learn":[2.785079289],"iteration":190,"passed_time":3.922456002,"remaining_time":16.63449927},
{"learn":[2.782509125],"iteration":191,"passed_time":3.953045563,"remaining_time":16.65632219},
{"learn":[2.780696935],"iteration":192,"passed_time":3.997085605,"remaining_time":16.73391279},
{"learn":[2.777727634],"iteration":193,"passed_time":4.038533776,"remaining_time":16.79946782},
{"learn":[2.775635112],"iteration":194,"passed_time":4.063178952,"remaining_time":16.794473},
{"learn":[2.77358531],"iteration":195,"passed_time":4.085717316,"remaining_time":16.78062469},
{"learn":[2.770808588],"iteration":196,"passed_time":4.114030475,"remaining_time":16.79025636},
{"learn":[2.76790154],"iteration":197,"passed_time":4.139890487,"remaining_time":16.78955586},
{"learn":[2.765428151],"iteration":198,"passed_time":4.160296462,"remaining_time":16.76662192},
{"learn":[2.762446877],"iteration":199,"passed_time":4.181332635,"remaining_time":16.7462372},
{"learn":[2.76043096],"iteration":200,"passed_time":4.200517782,"remaining_time":16.71847874},
{"learn":[2.757748202],"iteration":201,"passed_time":4.217818359,"remaining_time":16.68335084},
{"learn":[2.755661824],"iteration":202,"passed_time":4.236510734,"remaining_time":16.65386978},
{"learn":[2.754297448],"iteration":203,"passed_time":4.254332522,"remaining_time":16.62109324},
{"learn":[2.751929559],"iteration":204,"passed_time":4.270006309,"remaining_time":16.58012206},
{"learn":[2.749456824],"iteration":205,"passed_time":4.284913304,"remaining_time":16.53643727},
{"learn":[2.747173963],"iteration":206,"passed_time":4.300720844,"remaining_time":16.49648478},
{"learn":[2.744802483],"iteration":207,"passed_time":4.315240116,"remaining_time":16.45185294},
{"learn":[2.74275628],"iteration":208,"passed_time":4.331288674,"remaining_time":16.41330445},
{"learn":[2.739961682],"iteration":209,"passed_time":4.347334148,"remaining_time":16.37495862},
{"learn":[2.737789207],"iteration":210,"passed_time":4.361821794,"remaining_time":16.33099155},
{"learn":[2.736100372],"iteration":211,"passed_time":4.376830578,"remaining_time":16.28924211},
{"learn":[2.73432788],"iteration":212,"passed_time":4.392273889,"remaining_time":16.24935129},
{"learn":[2.73195018],"iteration":213,"passed_time":4.41106291,"remaining_time":16.22199304},
{"learn":[2.729223863],"iteration":214,"passed_time":4.429165558,"remaining_time":16.19220525},
{"learn":[2.727617937],"iteration":215,"passed_time":4.448416101,"remaining_time":16.1666974},
{"learn":[2.725470379],"iteration":216,"passed_time":4.466727313,"remaining_time":16.13785352},
{"learn":[2.72376251],"iteration":217,"passed_time":4.484691069,"remaining_time":16.10785829},
{"learn":[2.7216026],"iteration":218,"passed_time":4.508638532,"remaining_time":16.09933942},
{"learn":[2.720121729],"iteration":219,"passed_time":4.526459567,"remaining_time":16.06893146},
{"learn":[2.717553999],"iteration":220,"passed_time":4.544041204,"remaining_time":16.03779248},
{"learn":[2.715643927],"iteration":221,"passed_time":4.560757343,"remaining_time":16.00373861},
{"learn":[2.712872801],"iteration":222,"passed_time":4.584072075,"remaining_time":15.99286132},
{"learn":[2.710674084],"iteration":223,"passed_time":4.619214728,"remaining_time":16.02290109},
{"learn":[2.70807509],"iteration":224,"passed_time":4.642620971,"remaining_time":16.01188388},
{"learn":[2.706125427],"iteration":225,"passed_time":4.663849955,"remaining_time":15.99329077},
{"learn":[2.703721814],"iteration":226,"passed_time":4.711459865,"remaining_time":16.06462527},
{"learn":[2.702203591],"iteration":227,"passed_time":4.79358242,"remaining_time":16.25192636},
{"learn":[2.700047132],"iteration":228,"passed_time":4.833205946,"remaining_time":16.29360258},
{"learn":[2.698286025],"iteration":229,"passed_time":4.850885854,"remaining_time":16.26101301},
{"learn":[2.69640692],"iteration":230,"passed_time":4.866552792,"remaining_time":16.22184264},
{"learn":[2.694312859],"iteration":231,"passed_time":4.882181429,"remaining_time":16.18274793},
{"learn":[2.692431827],"iteration":232,"passed_time":4.898330135,"remaining_time":16.14556886},
{"learn":[2.690198987],"iteration":233,"passed_time":4.913424256,"remaining_time":16.10511284},
{"learn":[2.68859326],"iteration":234,"passed_time":4.930845051,"remaining_time":16.07245664},
{"learn":[2.686090734],"iteration":235,"passed_time":4.946366703,"remaining_time":16.03377342},
{"learn":[2.683636602],"iteration":236,"passed_time":4.961487378,"remaining_time":15.99399307},
{"learn":[2.681282517],"iteration":237,"passed_time":4.980222848,"remaining_time":15.96600854},
{"learn":[2.678804754],"iteration":238,"passed_time":4.998783467,"remaining_time":15.93754394},
{"learn":[2.677530147],"iteration":239,"passed_time":5.019900875,"remaining_time":15.91726903},
{"learn":[2.67520751],"iteration":240,"passed_time":5.056843071,"remaining_time":15.94689101},
{"learn":[2.673815834],"iteration":241,"passed_time":5.076641965,"remaining_time":15.92219526},
{"learn":[2.671583901],"iteration":242,"passed_time":5.096018249,"remaining_time":15.89622153},
{"learn":[2.670306903],"iteration":243,"passed_time":5.118984422,"remaining_time":15.88143938},
{"learn":[2.667169962],"iteration":244,"passed_time":5.14405998,"remaining_time":15.87309937},
{"learn":[2.665375827],"iteration":245,"passed_time":5.163118449,"remaining_time":15.84615622},
{"learn":[2.663041883],"iteration":246,"passed_time":5.185440399,"remaining_time":15.82923911},
{"learn":[2.661539497],"iteration":247,"passed_time":5.204901844,"remaining_time":15.8035931},
{"learn":[2.659970908],"iteration":248,"passed_time":5.226593861,"remaining_time":15.78473327},
{"learn":[2.658032386],"iteration":249,"passed_time":5.243760852,"remaining_time":15.7522576},
{"learn":[2.65695853],"iteration":250,"passed_time":5.259351886,"remaining_time":15.71519488},
{"learn":[2.655234432],"iteration":251,"passed_time":5.277748524,"remaining_time":15.68664145},
{"learn":[2.653205774],"iteration":252,"passed_time":5.29487061,"remaining_time":15.65440006},
{"learn":[2.652001241],"iteration":253,"passed_time":5.310463364,"remaining_time":15.61778005},
{"learn":[2.649880458],"iteration":254,"passed_time":5.330551383,"remaining_time":15.59447581},
{"learn":[2.646656063],"iteration":255,"passed_time":5.348428848,"remaining_time":15.56476364},
{"learn":[2.644726428],"iteration":256,"passed_time":5.37237691,"remaining_time":15.55271759},
{"learn":[2.642223396],"iteration":257,"passed_time":5.393099936,"remaining_time":15.53129168},
{"learn":[2.639605003],"iteration":258,"passed_time":5.412196526,"remaining_time":15.50521167},
{"learn":[2.637169677],"iteration":259,"passed_time":5.431479196,"remaining_time":15.47971571},
{"learn":[2.634985858],"iteration":260,"passed_time":5.453641257,"remaining_time":15.46243115},
{"learn":[2.633197719],"iteration":261,"passed_time":5.478107134,"remaining_time":15.45160753},
{"learn":[2.630334007],"iteration":262,"passed_time":5.498115285,"remaining_time":15.42817141},
{"learn":[2.62831686],"iteration":263,"passed_time":5.514674597,"remaining_time":15.39513325},
{"learn":[2.626564831],"iteration":264,"passed_time":5.530354491,"remaining_time":15.359777},
{"learn":[2.624603931],"iteration":265,"passed_time":5.543757719,"remaining_time":15.31827791},
{"learn":[2.622137662],"iteration":266,"passed_time":5.558830328,"remaining_time":15.2815785},
{"learn":[2.62050515],"iteration":267,"passed_time":5.573512746,"remaining_time":15.2439733},
{"learn":[2.618422901],"iteration":268,"passed_time":5.589326684,"remaining_time":15.20961759},
{"learn":[2.61630488],"iteration":269,"passed_time":5.61996416,"remaining_time":15.2155326},
{"learn":[2.61463023],"iteration":270,"passed_time":5.644498264,"remaining_time":15.20473702},
{"learn":[2.612695258],"iteration":271,"passed_time":5.66651435,"remaining_time":15.18709177},
{"learn":[2.610502155],"iteration":272,"passed_time":5.684961582,"remaining_time":15.15989755},
{"learn":[2.608230261],"iteration":273,"passed_time":5.705263852,"remaining_time":15.13768912},
{"learn":[2.606510669],"iteration":274,"passed_time":5.72712964,"remaining_time":15.11962225},
{"learn":[2.603690761],"iteration":275,"passed_time":5.746006781,"remaining_time":15.09367723},
{"learn":[2.601802393],"iteration":276,"passed_time":5.766498094,"remaining_time":15.07200224},
{"learn":[2.599639427],"iteration":277,"passed_time":5.783905961,"remaining_time":15.04231658},
{"learn":[2.598348347],"iteration":278,"passed_time":5.803591231,"remaining_time":15.01861243},
{"learn":[2.596462275],"iteration":279,"passed_time":5.819444967,"remaining_time":14.98507079},
{"learn":[2.594129547],"iteration":280,"passed_time":5.835133997,"remaining_time":14.95123302},
{"learn":[2.591850998],"iteration":281,"passed_time":5.852947556,"remaining_time":14.92294075},
{"learn":[2.589564603],"iteration":282,"passed_time":5.868854492,"remaining_time":14.88988525},
{"learn":[2.587513463],"iteration":283,"passed_time":5.884718125,"remaining_time":14.85684118},
{"learn":[2.58514757],"iteration":284,"passed_time":5.901047665,"remaining_time":14.82508817},
{"learn":[2.582602678],"iteration":285,"passed_time":5.91982913,"remaining_time":14.79957282},
{"learn":[2.580333603],"iteration":286,"passed_time":5.936392043,"remaining_time":14.76858508},
{"learn":[2.578183444],"iteration":287,"passed_time":5.951933215,"remaining_time":14.73516799},
{"learn":[2.576356442],"iteration":288,"passed_time":5.967218747,"remaining_time":14.7012448},
{"learn":[2.574949009],"iteration":289,"passed_time":5.987955962,"remaining_time":14.68081617},
{"learn":[2.573693826],"iteration":290,"passed_time":6.003389728,"remaining_time":14.64744573},
{"learn":[2.571697045],"iteration":291,"passed_time":6.017506294,"remaining_time":14.61099987},
{"learn":[2.570049568],"iteration":292,"passed_time":6.033021772,"remaining_time":14.57808674},
{"learn":[2.567964771],"iteration":293,"passed_time":6.051389606,"remaining_time":14.5521512},
{"learn":[2.566146239],"iteration":294,"passed_time":6.068474516,"remaining_time":14.52319664},
{"learn":[2.563526771],"iteration":295,"passed_time":6.085317016,"remaining_time":14.49374492},
{"learn":[2.561712612],"iteration":296,"passed_time":6.102316081,"remaining_time":14.46474923},
{"learn":[2.560392896],"iteration":297,"passed_time":6.124671058,"remaining_time":14.44846897},
{"learn":[2.558635351],"iteration":298,"passed_time":6.143323826,"remaining_time":14.42345594},
{"learn":[2.556563905],"iteration":299,"passed_time":6.16091111,"remaining_time":14.39599563},
{"learn":[2.55489345],"iteration":300,"passed_time":6.178343962,"remaining_time":14.36824177},
{"learn":[2.553714404],"iteration":301,"passed_time":6.202839003,"remaining_time":14.3569022},
{"learn":[2.551436792],"iteration":302,"passed_time":6.224172988,"remaining_time":14.33819388},
{"learn":[2.549626909],"iteration":303,"passed_time":6.242013777,"remaining_time":14.31145922},
{"learn":[2.547475457],"iteration":304,"passed_time":6.261095197,"remaining_time":14.28761396},
{"learn":[2.54590184],"iteration":305,"passed_time":6.281071217,"remaining_time":14.26583169},
{"learn":[2.544378512],"iteration":306,"passed_time":6.300104499,"remaining_time":14.24193004},
{"learn":[2.542452255],"iteration":307,"passed_time":6.31767327,"remaining_time":14.21476486},
{"learn":[2.540426445],"iteration":308,"passed_time":6.334898014,"remaining_time":14.18689135},
{"learn":[2.539122698],"iteration":309,"passed_time":6.360592584,"remaining_time":14.17796605},
{"learn":[2.537724663],"iteration":310,"passed_time":6.377866533,"remaining_time":14.15025051},
{"learn":[2.536148377],"iteration":311,"passed_time":6.394424949,"remaining_time":14.12102176},
{"learn":[2.534218943],"iteration":312,"passed_time":6.411229733,"remaining_time":14.09241552},
{"learn":[2.531841626],"iteration":313,"passed_time":6.427181024,"remaining_time":14.06201708},
{"learn":[2.529637371],"iteration":314,"passed_time":6.448254302,"remaining_time":14.04286492},
{"learn":[2.527744309],"iteration":315,"passed_time":6.465472931,"remaining_time":14.0153448},
{"learn":[2.525812244],"iteration":316,"passed_time":6.483613935,"remaining_time":13.98987991},
{"learn":[2.524715444],"iteration":317,"passed_time":6.503019437,"remaining_time":13.96717697},
{"learn":[2.523350398],"iteration":318,"passed_time":6.520058663,"remaining_time":13.93943576},
{"learn":[2.521901102],"iteration":319,"passed_time":6.541575276,"remaining_time":13.92128988},
{"learn":[2.520837361],"iteration":320,"passed_time":6.563626311,"remaining_time":13.90425511},
{"learn":[2.518941964],"iteration":321,"passed_time":6.583947549,"remaining_time":13.88354157},
{"learn":[2.517108921],"iteration":322,"passed_time":6.602172676,"remaining_time":13.85843057},
{"learn":[2.514909067],"iteration":323,"passed_time":6.62243828,"remaining_time":13.83762566},
{"learn":[2.51322406],"iteration":324,"passed_time":6.641748792,"remaining_time":13.81483749},
{"learn":[2.510995685],"iteration":325,"passed_time":6.659443872,"remaining_time":13.78872581},
{"learn":[2.509392078],"iteration":326,"passed_time":6.678772238,"remaining_time":13.76603207},
{"learn":[2.50754529],"iteration":327,"passed_time":6.696689449,"remaining_time":13.74046341},
{"learn":[2.506001181],"iteration":328,"passed_time":6.714441795,"remaining_time":13.71460452},
{"learn":[2.504424015],"iteration":329,"passed_time":6.73250284,"remaining_time":13.68942244},
{"learn":[2.503633337],"iteration":330,"passed_time":6.750593045,"remaining_time":13.66434242},
{"learn":[2.501605723],"iteration":331,"passed_time":6.775627756,"remaining_time":13.6532981},
{"learn":[2.499649926],"iteration":332,"passed_time":6.795540229,"remaining_time":13.63189451},
{"learn":[2.497363572],"iteration":333,"passed_time":6.81574641,"remaining_time":13.61108639},
{"learn":[2.495378101],"iteration":334,"passed_time":6.833858102,"remaining_time":13.5861179},
{"learn":[2.494056417],"iteration":335,"passed_time":6.853389315,"remaining_time":13.56399969},
{"learn":[2.492337985],"iteration":336,"passed_time":6.872125007,"remaining_time":13.54032939},
{"learn":[2.490986558],"iteration":337,"passed_time":6.893837662,"remaining_time":13.52252772},
{"learn":[2.489217735],"iteration":338,"passed_time":6.912426503,"remaining_time":13.49860279},
{"learn":[2.487642383],"iteration":339,"passed_time":6.931231388,"remaining_time":13.47512926},
{"learn":[2.486463858],"iteration":340,"passed_time":6.950717481,"remaining_time":13.45300158},
{"learn":[2.485148471],"iteration":341,"passed_time":6.969924019,"remaining_time":13.43035067},
{"learn":[2.482828444],"iteration":342,"passed_time":6.990688049,"remaining_time":13.41070769},
{"learn":[2.481044922],"iteration":343,"passed_time":7.011350783,"remaining_time":13.39086472},
{"learn":[2.479619292],"iteration":344,"passed_time":7.031726545,"remaining_time":13.37047134},
{"learn":[2.477136579],"iteration":345,"passed_time":7.052585793,"remaining_time":13.35099334},
{"learn":[2.476266208],"iteration":346,"passed_time":7.071104386,"remaining_time":13.32709587},
{"learn":[2.475242371],"iteration":347,"passed_time":7.090243419,"remaining_time":13.30439354},
{"learn":[2.473891329],"iteration":348,"passed_time":7.115408167,"remaining_time":13.29296884},
{"learn":[2.472258692],"iteration":349,"passed_time":7.139768278,"remaining_time":13.279969},
{"learn":[2.470870794],"iteration":350,"passed_time":7.162357163,"remaining_time":13.26362438},
{"learn":[2.469337815],"iteration":351,"passed_time":7.190583658,"remaining_time":13.25763862},
{"learn":[2.467853338],"iteration":352,"passed_time":7.219168968,"remaining_time":13.25218553},
{"learn":[2.466159646],"iteration":353,"passed_time":7.24003615,"remaining_time":13.23249545},
{"learn":[2.464089352],"iteration":354,"passed_time":7.261260012,"remaining_time":13.2134478},
{"learn":[2.462651254],"iteration":355,"passed_time":7.282697075,"remaining_time":13.19477419},
{"learn":[2.460675569],"iteration":356,"passed_time":7.303830618,"remaining_time":13.17553759},
{"learn":[2.458274151],"iteration":357,"passed_time":7.327846032,"remaining_time":13.16146648},
{"learn":[2.457188766],"iteration":358,"passed_time":7.347200866,"remaining_time":13.13900545},
{"learn":[2.455362473],"iteration":359,"passed_time":7.367565756,"remaining_time":13.11836014},
{"learn":[2.454548363],"iteration":360,"passed_time":7.386325988,"remaining_time":13.09487156},
{"learn":[2.453123364],"iteration":361,"passed_time":7.407057042,"remaining_time":13.07488798},
{"learn":[2.45161808],"iteration":362,"passed_time":7.429316141,"remaining_time":13.05758594},
{"learn":[2.450532112],"iteration":363,"passed_time":7.450467608,"remaining_time":13.03831831},
{"learn":[2.449171691],"iteration":364,"passed_time":7.468732164,"remaining_time":13.01401002},
{"learn":[2.447883418],"iteration":365,"passed_time":7.489036086,"remaining_time":12.99327299},
{"learn":[2.446317446],"iteration":366,"passed_time":7.51147583,"remaining_time":12.976228},
{"learn":[2.444894774],"iteration":367,"passed_time":7.532233977,"remaining_time":12.95626116},
{"learn":[2.443453242],"iteration":368,"passed_time":7.552257887,"remaining_time":12.93503248},
{"learn":[2.44225387],"iteration":369,"passed_time":7.574887565,"remaining_time":12.9182542},
{"learn":[2.440999563],"iteration":370,"passed_time":7.596759732,"remaining_time":12.90015804},
{"learn":[2.439937791],"iteration":371,"passed_time":7.615701074,"remaining_time":12.87708596},
{"learn":[2.438374479],"iteration":372,"passed_time":7.635344036,"remaining_time":12.8552173},
{"learn":[2.436819071],"iteration":373,"passed_time":7.659308405,"remaining_time":12.84060527},
{"learn":[2.435284399],"iteration":374,"passed_time":7.683418134,"remaining_time":12.826186},
{"learn":[2.433667681],"iteration":375,"passed_time":7.707454738,"remaining_time":12.81159365},
{"learn":[2.432690251],"iteration":376,"passed_time":7.726677742,"remaining_time":12.78898385},
{"learn":[2.430595726],"iteration":377,"passed_time":7.747219703,"remaining_time":12.76856581},
{"learn":[2.428498191],"iteration":378,"passed_time":7.765686605,"remaining_time":12.7447416},
{"learn":[2.426999078],"iteration":379,"passed_time":7.786073052,"remaining_time":12.72408254},
{"learn":[2.425445259],"iteration":380,"passed_time":7.805449776,"remaining_time":12.70178179},
{"learn":[2.424024771],"iteration":381,"passed_time":7.825694116,"remaining_time":12.68090225},
{"learn":[2.422817502],"iteration":382,"passed_time":7.845353382,"remaining_time":12.65908196},
{"learn":[2.421474097],"iteration":383,"passed_time":7.867850388,"remaining_time":12.64183252},
{"learn":[2.419970253],"iteration":384,"passed_time":7.89249924,"remaining_time":12.62799878},
{"learn":[2.41842029],"iteration":385,"passed_time":7.91294098,"remaining_time":12.60740597},
{"learn":[2.416904476],"iteration":386,"passed_time":7.93633445,"remaining_time":12.59149703},
{"learn":[2.415794775],"iteration":387,"passed_time":7.956554026,"remaining_time":12.5705351},
{"learn":[2.414394147],"iteration":388,"passed_time":7.974552898,"remaining_time":12.54608322},
{"learn":[2.412984241],"iteration":389,"passed_time":7.99298667,"remaining_time":12.52234578},
{"learn":[2.412018784],"iteration":390,"passed_time":8.013097569,"remaining_time":12.50125196},
{"learn":[2.410293684],"iteration":391,"passed_time":8.033184787,"remaining_time":12.48012636},
{"learn":[2.408423741],"iteration":392,"passed_time":8.052750668,"remaining_time":12.45819951},
{"learn":[2.40656596],"iteration":393,"passed_time":8.075237036,"remaining_time":12.44078396},
{"learn":[2.405165268],"iteration":394,"passed_time":8.095572532,"remaining_time":12.42004292},
{"learn":[2.403430241],"iteration":395,"passed_time":8.119482312,"remaining_time":12.40476464},
{"learn":[2.401872334],"iteration":396,"passed_time":8.139256804,"remaining_time":12.38315141},
{"learn":[2.400590497],"iteration":397,"passed_time":8.163613824,"remaining_time":12.36849029},
{"learn":[2.399408086],"iteration":398,"passed_time":8.184677276,"remaining_time":12.34881133},
{"learn":[2.398109668],"iteration":399,"passed_time":8.203215835,"remaining_time":12.32533179},
{"learn":[2.396476357],"iteration":400,"passed_time":8.224620777,"remaining_time":12.30616575},
{"learn":[2.395091162],"iteration":401,"passed_time":8.244004677,"remaining_time":12.28397712},
{"learn":[2.393936928],"iteration":402,"passed_time":8.262983696,"remaining_time":12.26120161},
{"learn":[2.392814015],"iteration":403,"passed_time":8.282855983,"remaining_time":12.23976491},
{"learn":[2.391047097],"iteration":404,"passed_time":8.318536552,"remaining_time":12.24159947},
{"learn":[2.389570409],"iteration":405,"passed_time":8.34345614,"remaining_time":12.22747883},
{"learn":[2.388298701],"iteration":406,"passed_time":8.362138642,"remaining_time":12.20420234},
{"learn":[2.386886261],"iteration":407,"passed_time":8.381108409,"remaining_time":12.1813659},
{"learn":[2.385440498],"iteration":408,"passed_time":8.400046511,"remaining_time":12.15850253},
{"learn":[2.384059751],"iteration":409,"passed_time":8.419848742,"remaining_time":12.13690392},
{"learn":[2.38275805],"iteration":410,"passed_time":8.438309617,"remaining_time":12.1133885},
{"learn":[2.38166591],"iteration":411,"passed_time":8.457925837,"remaining_time":12.09154932},
{"learn":[2.380499316],"iteration":412,"passed_time":8.478952441,"remaining_time":12.0717289},
{"learn":[2.3789771],"iteration":413,"passed_time":8.49868078,"remaining_time":12.05006188},
{"learn":[2.377475989],"iteration":414,"passed_time":8.52314437,"remaining_time":12.0350906},
{"learn":[2.376297125],"iteration":415,"passed_time":8.551163562,"remaining_time":12.02507376},
{"learn":[2.374800005],"iteration":416,"passed_time":8.576725019,"remaining_time":12.01152856},
{"learn":[2.373726428],"iteration":417,"passed_time":8.600035923,"remaining_time":11.99478694},
{"learn":[2.372982671],"iteration":418,"passed_time":8.624570501,"remaining_time":11.97971368},
{"learn":[2.372092159],"iteration":419,"passed_time":8.647676581,"remaining_time":11.96261927},
{"learn":[2.370621433],"iteration":420,"passed_time":8.671761229,"remaining_time":11.94684445},
{"learn":[2.368846042],"iteration":421,"passed_time":8.693163752,"remaining_time":11.92735027},
{"learn":[2.367649914],"iteration":422,"passed_time":8.715682172,"remaining_time":11.90937186},
{"learn":[2.366276761],"iteration":423,"passed_time":8.73684329,"remaining_time":11.88952495},
{"learn":[2.364592731],"iteration":424,"passed_time":8.762966739,"remaining_time":11.87639727},
{"learn":[2.362681171],"iteration":425,"passed_time":8.783510705,"remaining_time":11.85567759},
{"learn":[2.361382287],"iteration":426,"passed_time":8.804449694,"remaining_time":11.83548975},
{"learn":[2.360382477],"iteration":427,"passed_time":8.825334083,"remaining_time":11.8152253},
{"learn":[2.359287797],"iteration":428,"passed_time":8.846451611,"remaining_time":11.79526881},
{"learn":[2.358132902],"iteration":429,"passed_time":8.866857761,"remaining_time":11.77436228},
{"learn":[2.356647722],"iteration":430,"passed_time":8.895107881,"remaining_time":11.76383177},
{"learn":[2.355454742],"iteration":431,"passed_time":8.918317757,"remaining_time":11.74658056},
{"learn":[2.354121606],"iteration":432,"passed_time":8.942630232,"remaining_time":11.7307482},
{"learn":[2.353263888],"iteration":433,"passed_time":8.972154909,"remaining_time":11.72168625},
{"learn":[2.351871994],"iteration":434,"passed_time":8.996057253,"remaining_time":11.70521473},
{"learn":[2.350819941],"iteration":435,"passed_time":9.022205037,"remaining_time":11.69161891},
{"learn":[2.349776074],"iteration":436,"passed_time":9.053916917,"remaining_time":11.68514678},
{"learn":[2.348427786],"iteration":437,"passed_time":9.076456593,"remaining_time":11.66676955},
{"learn":[2.347111324],"iteration":438,"passed_time":9.097386995,"remaining_time":11.64631319},
{"learn":[2.346079808],"iteration":439,"passed_time":9.11790284,"remaining_time":11.62532612},
{"learn":[2.343956271],"iteration":440,"passed_time":9.14349142,"remaining_time":11.61078276},
{"learn":[2.342855556],"iteration":441,"passed_time":9.165420326,"remaining_time":11.591561},
{"learn":[2.34182976],"iteration":442,"passed_time":9.192023016,"remaining_time":11.57821409},
{"learn":[2.340716012],"iteration":443,"passed_time":9.213145568,"remaining_time":11.55793262},
{"learn":[2.339436488],"iteration":444,"passed_time":9.234267231,"remaining_time":11.53764625},
{"learn":[2.338032236],"iteration":445,"passed_time":9.256447834,"remaining_time":11.51867387},
{"learn":[2.336774746],"iteration":446,"passed_time":9.278601237,"remaining_time":11.49965343},
{"learn":[2.335144724],"iteration":447,"passed_time":9.305605305,"remaining_time":11.48660655},
{"learn":[2.334241481],"iteration":448,"passed_time":9.329548588,"remaining_time":11.46973457},
{"learn":[2.333361843],"iteration":449,"passed_time":9.353337574,"remaining_time":11.45264223},
{"learn":[2.332184992],"iteration":450,"passed_time":9.378640909,"remaining_time":11.43736696},
{"learn":[2.331189232],"iteration":451,"passed_time":9.408581722,"remaining_time":11.42768001},
{"learn":[2.330032288],"iteration":452,"passed_time":9.441957806,"remaining_time":11.42205933},
{"learn":[2.32904696],"iteration":453,"passed_time":9.468413036,"remaining_time":11.40797782},
{"learn":[2.327893616],"iteration":454,"passed_time":9.493690266,"remaining_time":11.39242832},
{"learn":[2.326691995],"iteration":455,"passed_time":9.516397021,"remaining_time":11.37376398},
{"learn":[2.325384729],"iteration":456,"passed_time":9.541251052,"remaining_time":11.35763801},
{"learn":[2.32420683],"iteration":457,"passed_time":9.562302384,"remaining_time":11.33696549},
{"learn":[2.32260241],"iteration":458,"passed_time":9.583475487,"remaining_time":11.31643511},
{"learn":[2.321582923],"iteration":459,"passed_time":9.605435086,"remaining_time":11.29682692},
{"learn":[2.320443063],"iteration":460,"passed_time":9.632149341,"remaining_time":11.28277797},
{"learn":[2.319299498],"iteration":461,"passed_time":9.652916944,"remaining_time":11.26173643},
{"learn":[2.318134775],"iteration":462,"passed_time":9.674705626,"remaining_time":11.24188256},
{"learn":[2.317456048],"iteration":463,"passed_time":9.70152704,"remaining_time":11.22784487},
{"learn":[2.316506537],"iteration":464,"passed_time":9.728734889,"remaining_time":11.21419764},
{"learn":[2.315185802],"iteration":465,"passed_time":9.753918823,"remaining_time":11.19816861},
{"learn":[2.313705578],"iteration":466,"passed_time":9.780545805,"remaining_time":11.18375045},
{"learn":[2.312808475],"iteration":467,"passed_time":9.803794123,"remaining_time":11.1654322},
{"learn":[2.312050847],"iteration":468,"passed_time":9.828618992,"remaining_time":11.14888125},
{"learn":[2.310720042],"iteration":469,"passed_time":9.857259818,"remaining_time":11.1366063},
{"learn":[2.309872772],"iteration":470,"passed_time":9.879056224,"remaining_time":11.11656008},
{"learn":[2.308612765],"iteration":471,"passed_time":9.902006247,"remaining_time":11.09779937},
{"learn":[2.307714374],"iteration":472,"passed_time":9.922359141,"remaining_time":11.07612183},
{"learn":[2.306260366],"iteration":473,"passed_time":9.94396843,"remaining_time":11.05584676},
{"learn":[2.305141376],"iteration":474,"passed_time":9.964359949,"remaining_time":11.03421754},
{"learn":[2.303974586],"iteration":475,"passed_time":9.985482131,"remaining_time":11.01339941},
{"learn":[2.303437692],"iteration":476,"passed_time":10.00717283,"remaining_time":10.99320453},
{"learn":[2.301453739],"iteration":477,"passed_time":10.03083413,"remaining_time":10.97515952},
{"learn":[2.300258396],"iteration":478,"passed_time":10.05660422,"remaining_time":10.95938915},
{"learn":[2.299402445],"iteration":479,"passed_time":10.09185449,"remaining_time":10.95386707},
{"learn":[2.29850632],"iteration":480,"passed_time":10.11814122,"remaining_time":10.93853104},
{"learn":[2.297691041],"iteration":481,"passed_time":10.14927312,"remaining_time":10.9283667},
{"learn":[2.297022948],"iteration":482,"passed_time":10.17543028,"remaining_time":10.91278031},
{"learn":[2.295789033],"iteration":483,"passed_time":10.19992229,"remaining_time":10.89537154},
{"learn":[2.294950814],"iteration":484,"passed_time":10.22248898,"remaining_time":10.87588518},
{"learn":[2.293810277],"iteration":485,"passed_time":10.24329708,"remaining_time":10.85452262},
{"learn":[2.292581531],"iteration":486,"passed_time":10.26356835,"remaining_time":10.83259575},
{"learn":[2.292083554],"iteration":487,"passed_time":10.28558487,"remaining_time":10.81251033},
{"learn":[2.291181535],"iteration":488,"passed_time":10.31019704,"remaining_time":10.79513473},
{"learn":[2.290146123],"iteration":489,"passed_time":10.33094505,"remaining_time":10.77369983},
{"learn":[2.288970977],"iteration":490,"passed_time":10.35320429,"remaining_time":10.75383745},
{"learn":[2.288175578],"iteration":491,"passed_time":10.37384899,"remaining_time":10.73229499},
{"learn":[2.286725448],"iteration":492,"passed_time":10.39551047,"remaining_time":10.71180389},
{"learn":[2.285300346],"iteration":493,"passed_time":10.41633093,"remaining_time":10.69044491},
{"learn":[2.284498374],"iteration":494,"passed_time":10.43853376,"remaining_time":10.67050118},
{"learn":[2.28337097],"iteration":495,"passed_time":10.46167272,"remaining_time":10.65150145},
{"learn":[2.282008157],"iteration":496,"passed_time":10.48652121,"remaining_time":10.63421869},
{"learn":[2.281329686],"iteration":497,"passed_time":10.51129289,"remaining_time":10.61682796},
{"learn":[2.280414419],"iteration":498,"passed_time":10.54431126,"remaining_time":10.60770391},
{"learn":[2.279811905],"iteration":499,"passed_time":10.56922846,"remaining_time":10.59036692},
{"learn":[2.278882679],"iteration":500,"passed_time":10.59826292,"remaining_time":10.5771087},
{"learn":[2.277209567],"iteration":501,"passed_time":10.6222505,"remaining_time":10.55877091},
{"learn":[2.275534742],"iteration":502,"passed_time":10.64492172,"remaining_time":10.53910739},
{"learn":[2.274917474],"iteration":503,"passed_time":10.6664617,"remaining_time":10.5183164},
{"learn":[2.273957047],"iteration":504,"passed_time":10.68691123,"remaining_time":10.49645142},
{"learn":[2.272318896],"iteration":505,"passed_time":10.70759048,"remaining_time":10.47481677},
{"learn":[2.270826287],"iteration":506,"passed_time":10.72863072,"remaining_time":10.45353762},
{"learn":[2.269982197],"iteration":507,"passed_time":10.75090051,"remaining_time":10.43345266},
{"learn":[2.268676012],"iteration":508,"passed_time":10.77385459,"remaining_time":10.41402054},
{"learn":[2.267761071],"iteration":509,"passed_time":10.79500726,"remaining_time":10.39284032},
{"learn":[2.266909865],"iteration":510,"passed_time":10.81546145,"remaining_time":10.37099043},
{"learn":[2.266249138],"iteration":511,"passed_time":10.83884452,"remaining_time":10.3519433},
{"learn":[2.265023489],"iteration":512,"passed_time":10.86559924,"remaining_time":10.3360866},
{"learn":[2.264425311],"iteration":513,"passed_time":10.88754641,"remaining_time":10.31563249},
{"learn":[2.263502099],"iteration":514,"passed_time":10.91136802,"remaining_time":10.29694147},
{"learn":[2.262786445],"iteration":515,"passed_time":10.93947708,"remaining_time":10.28226043},
{"learn":[2.261829833],"iteration":516,"passed_time":10.96526685,"remaining_time":10.2653562},
{"learn":[2.26003154],"iteration":517,"passed_time":11.04535538,"remaining_time":10.29904758},
{"learn":[2.258701512],"iteration":518,"passed_time":11.11213434,"remaining_time":10.31993979},
{"learn":[2.257536679],"iteration":519,"passed_time":11.1463487,"remaining_time":10.31037255},
{"learn":[2.25636456],"iteration":520,"passed_time":11.20115845,"remaining_time":10.31968533},
{"learn":[2.255506067],"iteration":521,"passed_time":11.22951543,"remaining_time":10.30447872},
{"learn":[2.254220175],"iteration":522,"passed_time":11.26318302,"remaining_time":10.29407549},
{"learn":[2.253548381],"iteration":523,"passed_time":11.29829736,"remaining_time":10.28490046},
{"learn":[2.252451739],"iteration":524,"passed_time":11.33031482,"remaining_time":10.27281877},
{"learn":[2.251452594],"iteration":525,"passed_time":11.36508793,"remaining_time":10.26314975},
{"learn":[2.250603845],"iteration":526,"passed_time":11.39041242,"remaining_time":10.24488707},
{"learn":[2.249403693],"iteration":527,"passed_time":11.41580783,"remaining_time":10.22666118},
{"learn":[2.24857662],"iteration":528,"passed_time":11.43838156,"remaining_time":10.20589054},
{"learn":[2.247266067],"iteration":529,"passed_time":11.46029229,"remaining_time":10.1845239},
{"learn":[2.245937719],"iteration":530,"passed_time":11.48265861,"remaining_time":10.16355847},
{"learn":[2.244998788],"iteration":531,"passed_time":11.50466255,"remaining_time":10.1422683},
{"learn":[2.244398331],"iteration":532,"passed_time":11.52694762,"remaining_time":10.1212223},
{"learn":[2.243659792],"iteration":533,"passed_time":11.55009646,"remaining_time":10.10092705},
{"learn":[2.242522223],"iteration":534,"passed_time":11.57429439,"remaining_time":10.08153492},
{"learn":[2.241377862],"iteration":535,"passed_time":11.59745252,"remaining_time":10.0612228},
{"learn":[2.240577528],"iteration":536,"passed_time":11.62420669,"remaining_time":10.04400727},
{"learn":[2.240127642],"iteration":537,"passed_time":11.65022521,"remaining_time":10.02612318},
{"learn":[2.239148971],"iteration":538,"passed_time":11.67555092,"remaining_time":10.00761508},
{"learn":[2.237893009],"iteration":539,"passed_time":11.70534361,"remaining_time":9.992895197},
{"learn":[2.236835647],"iteration":540,"passed_time":11.73012315,"remaining_time":9.973857023},
{"learn":[2.235874659],"iteration":541,"passed_time":11.75580071,"remaining_time":9.95555817},
{"learn":[2.234973995],"iteration":542,"passed_time":11.78090923,"remaining_time":9.936752166},
{"learn":[2.234041494],"iteration":543,"passed_time":11.80377876,"remaining_time":9.916042081},
{"learn":[2.233311989],"iteration":544,"passed_time":11.82593097,"remaining_time":9.894723894},
{"learn":[2.232424103],"iteration":545,"passed_time":11.8530626,"remaining_time":9.877552165},
{"learn":[2.231987097],"iteration":546,"passed_time":11.87330571,"remaining_time":9.854626674},
{"learn":[2.231417986],"iteration":547,"passed_time":11.89558329,"remaining_time":9.833392755},
{"learn":[2.230215655],"iteration":548,"passed_time":11.92237782,"remaining_time":9.815873909},
{"learn":[2.229502326],"iteration":549,"passed_time":11.95314026,"remaining_time":9.801575013},
{"learn":[2.228194363],"iteration":550,"passed_time":11.97892479,"remaining_time":9.783150917},
{"learn":[2.227231891],"iteration":551,"passed_time":12.00537398,"remaining_time":9.765240789},
{"learn":[2.226462127],"iteration":552,"passed_time":12.03093088,"remaining_time":9.746576912},
{"learn":[2.225376743],"iteration":553,"passed_time":12.05295838,"remaining_time":9.725040422},
{"learn":[2.224085207],"iteration":554,"passed_time":12.08040177,"remaining_time":9.707854396},
{"learn":[2.223050375],"iteration":555,"passed_time":12.10452139,"remaining_time":9.687971255},
{"learn":[2.2222465],"iteration":556,"passed_time":12.12770389,"remaining_time":9.667325901},
{"learn":[2.221159835],"iteration":557,"passed_time":12.1491459,"remaining_time":9.645289665},
{"learn":[2.220127092],"iteration":558,"passed_time":12.16983539,"remaining_time":9.622660544},
{"learn":[2.219069679],"iteration":559,"passed_time":12.19342446,"remaining_time":9.602321761},
{"learn":[2.218323997],"iteration":560,"passed_time":12.21634521,"remaining_time":9.581447226},
{"learn":[2.217458547],"iteration":561,"passed_time":12.24100187,"remaining_time":9.56192139},
{"learn":[2.216368733],"iteration":562,"passed_time":12.26599618,"remaining_time":9.542640008},
{"learn":[2.215746764],"iteration":563,"passed_time":12.28953295,"remaining_time":9.522209039},
{"learn":[2.214074456],"iteration":564,"passed_time":12.31998823,"remaining_time":9.507105964},
{"learn":[2.213237998],"iteration":565,"passed_time":12.35616151,"remaining_time":9.496343211},
{"learn":[2.212251951],"iteration":566,"passed_time":12.37676036,"remaining_time":9.473569658},
{"learn":[2.21075351],"iteration":567,"passed_time":12.40012729,"remaining_time":9.452913941},
{"learn":[2.210128318],"iteration":568,"passed_time":12.42254038,"remaining_time":9.431524507},
{"learn":[2.209382628],"iteration":569,"passed_time":12.44261637,"remaining_time":9.408364305},
{"learn":[2.208010884],"iteration":570,"passed_time":12.46913987,"remaining_time":9.390070308},
{"learn":[2.206706945],"iteration":571,"passed_time":12.49127382,"remaining_time":9.368455368},
{"learn":[2.205851648],"iteration":572,"passed_time":12.51197521,"remaining_time":9.345768569},
{"learn":[2.204962991],"iteration":573,"passed_time":12.53572691,"remaining_time":9.325357825},
{"learn":[2.203795954],"iteration":574,"passed_time":12.55839825,"remaining_time":9.304135053},
{"learn":[2.203289319],"iteration":575,"passed_time":12.57792065,"remaining_time":9.280583813},
{"learn":[2.202279157],"iteration":576,"passed_time":12.60232687,"remaining_time":9.260635345},
{"learn":[2.201218661],"iteration":577,"passed_time":12.62189173,"remaining_time":9.237128375},
{"learn":[2.200260726],"iteration":578,"passed_time":12.64339721,"remaining_time":9.215049435},
{"learn":[2.199457303],"iteration":579,"passed_time":12.66352118,"remaining_time":9.191969681},
{"learn":[2.198533025],"iteration":580,"passed_time":12.68435187,"remaining_time":9.169410991},
{"learn":[2.197509585],"iteration":581,"passed_time":12.70500592,"remaining_time":9.146731065},
{"learn":[2.196670742],"iteration":582,"passed_time":12.72701636,"remaining_time":9.125030598},
{"learn":[2.196113402],"iteration":583,"passed_time":12.7533326,"remaining_time":9.106403589},
{"learn":[2.195129651],"iteration":584,"passed_time":12.77707057,"remaining_time":9.085916847},
{"learn":[2.194166731],"iteration":585,"passed_time":12.80091316,"remaining_time":9.06549311},
{"learn":[2.193443043],"iteration":586,"passed_time":12.82513443,"remaining_time":9.045324796},
{"learn":[2.192319523],"iteration":587,"passed_time":12.84715008,"remaining_time":9.023593509},
{"learn":[2.191503027],"iteration":588,"passed_time":12.86720681,"remaining_time":9.000491012},
{"learn":[2.190311667],"iteration":589,"passed_time":12.89668438,"remaining_time":8.983961492},
{"learn":[2.189484776],"iteration":590,"passed_time":12.91932672,"remaining_time":8.962646289},
{"learn":[2.18806174],"iteration":591,"passed_time":12.9440261,"remaining_time":8.942747764},
{"learn":[2.186995075],"iteration":592,"passed_time":12.97170292,"remaining_time":8.924881608},
{"learn":[2.185540367],"iteration":593,"passed_time":12.99394532,"remaining_time":8.903258828},
{"learn":[2.184582746],"iteration":594,"passed_time":13.02031574,"remaining_time":8.884450743},
{"learn":[2.183709748],"iteration":595,"passed_time":13.04181176,"remaining_time":8.862304972},
{"learn":[2.182929196],"iteration":596,"passed_time":13.06318792,"remaining_time":8.840080271},
{"learn":[2.181869326],"iteration":597,"passed_time":13.08761877,"remaining_time":8.819916996},
{"learn":[2.181424745],"iteration":598,"passed_time":13.1097157,"remaining_time":8.79817314},
{"learn":[2.180515809],"iteration":599,"passed_time":13.1309541,"remaining_time":8.775854322},
{"learn":[2.179824092],"iteration":600,"passed_time":13.15451048,"remaining_time":8.755081853},
{"learn":[2.178926775],"iteration":601,"passed_time":13.17771915,"remaining_time":8.734069669},
{"learn":[2.177562856],"iteration":602,"passed_time":13.20853185,"remaining_time":8.718069115},
{"learn":[2.176650277],"iteration":603,"passed_time":13.23262874,"remaining_time":8.697605311},
{"learn":[2.175271505],"iteration":604,"passed_time":13.25696743,"remaining_time":8.67728777},
{"learn":[2.174433721],"iteration":605,"passed_time":13.28413612,"remaining_time":8.658801599},
{"learn":[2.173574967],"iteration":606,"passed_time":13.30773125,"remaining_time":8.637967235},
{"learn":[2.172346815],"iteration":607,"passed_time":13.32975037,"remaining_time":8.616105092},
{"learn":[2.171333965],"iteration":608,"passed_time":13.35167939,"remaining_time":8.594184437},
{"learn":[2.170930595],"iteration":609,"passed_time":13.37285689,"remaining_time":8.571782037},
{"learn":[2.170282633],"iteration":610,"passed_time":13.39470398,"remaining_time":8.549811048},
{"learn":[2.169986092],"iteration":611,"passed_time":13.4172207,"remaining_time":8.528266098},
{"learn":[2.169255597],"iteration":612,"passed_time":13.44602677,"remaining_time":8.510698835},
{"learn":[2.16827941],"iteration":613,"passed_time":13.47271364,"remaining_time":8.491759247},
{"learn":[2.167806695],"iteration":614,"passed_time":13.49659323,"remaining_time":8.471032499},
{"learn":[2.166740926],"iteration":615,"passed_time":13.5212696,"remaining_time":8.450793498},
{"learn":[2.16597466],"iteration":616,"passed_time":13.54247168,"remaining_time":8.428377833},
{"learn":[2.16469154],"iteration":617,"passed_time":13.56631088,"remaining_time":8.407600433},
{"learn":[2.163777401],"iteration":618,"passed_time":13.59023961,"remaining_time":8.386868389},
{"learn":[2.162712854],"iteration":619,"passed_time":13.61792467,"remaining_time":8.368434353},
{"learn":[2.162003871],"iteration":620,"passed_time":13.64653041,"remaining_time":8.350533908},
{"learn":[2.161069096],"iteration":621,"passed_time":13.67114131,"remaining_time":8.330164879},
{"learn":[2.160311491],"iteration":622,"passed_time":13.69465588,"remaining_time":8.30911705},
{"learn":[2.159442541],"iteration":623,"passed_time":13.71743731,"remaining_time":8.287618375},
{"learn":[2.158561072],"iteration":624,"passed_time":13.73963895,"remaining_time":8.265766795},
{"learn":[2.157707404],"iteration":625,"passed_time":13.76101477,"remaining_time":8.243419389},
{"learn":[2.157169102],"iteration":626,"passed_time":13.78104874,"remaining_time":8.220274684},
{"learn":[2.156547017],"iteration":627,"passed_time":13.80107993,"remaining_time":8.197138236},
{"learn":[2.155471315],"iteration":628,"passed_time":13.82513221,"remaining_time":8.176389795},
{"learn":[2.155074191],"iteration":629,"passed_time":13.84702698,"remaining_time":8.154360333},
{"learn":[2.154427288],"iteration":630,"passed_time":13.87059162,"remaining_time":8.13331046},
{"learn":[2.1537704],"iteration":631,"passed_time":13.89212444,"remaining_time":8.111066327},
{"learn":[2.15311765],"iteration":632,"passed_time":13.91254404,"remaining_time":8.08817726},
{"learn":[2.152146611],"iteration":633,"passed_time":13.93422521,"remaining_time":8.066026268},
{"learn":[2.151466312],"iteration":634,"passed_time":13.9535122,"remaining_time":8.042496795},
{"learn":[2.150691416],"iteration":635,"passed_time":13.97518604,"remaining_time":8.02035048},
{"learn":[2.149934346],"iteration":636,"passed_time":14.00053916,"remaining_time":8.000308092},
{"learn":[2.149432698],"iteration":637,"passed_time":14.02340205,"remaining_time":7.978832199},
{"learn":[2.148609453],"iteration":638,"passed_time":14.0472164,"remaining_time":7.957890983},
{"learn":[2.147763265],"iteration":639,"passed_time":14.07177408,"remaining_time":7.937360067},
{"learn":[2.146914787],"iteration":640,"passed_time":14.0998263,"remaining_time":7.918779202},
{"learn":[2.146235531],"iteration":641,"passed_time":14.12269119,"remaining_time":7.897268128},
{"learn":[2.145506488],"iteration":642,"passed_time":14.15040132,"remaining_time":7.878450502},
{"learn":[2.144912598],"iteration":643,"passed_time":14.1753502,"remaining_time":7.858074569},
{"learn":[2.144102367],"iteration":644,"passed_time":14.2036029,"remaining_time":7.83950796},
{"learn":[2.143420056],"iteration":645,"passed_time":14.2239791,"remaining_time":7.816582943},
{"learn":[2.142876283],"iteration":646,"passed_time":14.24656478,"remaining_time":7.794874699},
{"learn":[2.141745182],"iteration":647,"passed_time":14.26855883,"remaining_time":7.772841459},
{"learn":[2.140036207],"iteration":648,"passed_time":14.29363399,"remaining_time":7.75247945},
{"learn":[2.139254212],"iteration":649,"passed_time":14.31748254,"remaining_time":7.731440573},
{"learn":[2.138556919],"iteration":650,"passed_time":14.33910592,"remaining_time":7.709196733},
{"learn":[2.137088638],"iteration":651,"passed_time":14.36165745,"remaining_time":7.687451609},
{"learn":[2.135953057],"iteration":652,"passed_time":14.38237748,"remaining_time":7.664727967},
{"learn":[2.135041384],"iteration":653,"passed_time":14.40485485,"remaining_time":7.642942862},
{"learn":[2.134231146],"iteration":654,"passed_time":14.42691724,"remaining_time":7.620936434},
{"learn":[2.133212733],"iteration":655,"passed_time":14.44591327,"remaining_time":7.597317194},
{"learn":[2.132348303],"iteration":656,"passed_time":14.46692878,"remaining_time":7.574769409},
{"learn":[2.131559993],"iteration":657,"passed_time":14.48633741,"remaining_time":7.551388648},
{"learn":[2.130114337],"iteration":658,"passed_time":14.51070645,"remaining_time":7.530594241},
{"learn":[2.129619329],"iteration":659,"passed_time":14.53133947,"remaining_time":7.507858724},
{"learn":[2.129067071],"iteration":660,"passed_time":14.5558454,"remaining_time":7.487121691},
{"learn":[2.128431565],"iteration":661,"passed_time":14.57416827,"remaining_time":7.463207016},
{"learn":[2.127746656],"iteration":662,"passed_time":14.59243809,"remaining_time":7.439282164},
{"learn":[2.12668694],"iteration":663,"passed_time":14.6103207,"remaining_time":7.415177825},
{"learn":[2.126036709],"iteration":664,"passed_time":14.62816875,"remaining_time":7.391074737},
{"learn":[2.125467857],"iteration":665,"passed_time":14.64686681,"remaining_time":7.367417991},
{"learn":[2.124562298],"iteration":666,"passed_time":14.66669623,"remaining_time":7.344342642},
{"learn":[2.124094341],"iteration":667,"passed_time":14.68411335,"remaining_time":7.320074469},
{"learn":[2.123323524],"iteration":668,"passed_time":14.70148905,"remaining_time":7.295806223},
{"learn":[2.122655892],"iteration":669,"passed_time":14.72231259,"remaining_time":7.273261889},
{"learn":[2.122211971],"iteration":670,"passed_time":14.74190557,"remaining_time":7.250117492},
{"learn":[2.121672147],"iteration":671,"passed_time":14.76682916,"remaining_time":7.229593443},
{"learn":[2.121145298],"iteration":672,"passed_time":14.79098542,"remaining_time":7.208682343},
{"learn":[2.120511489],"iteration":673,"passed_time":14.81320905,"remaining_time":7.186823975},
{"learn":[2.119772352],"iteration":674,"passed_time":14.83579391,"remaining_time":7.165138984},
{"learn":[2.119149851],"iteration":675,"passed_time":14.85647972,"remaining_time":7.142538326},
{"learn":[2.118512295],"iteration":676,"passed_time":14.87824762,"remaining_time":7.120461194},
{"learn":[2.118084238],"iteration":677,"passed_time":14.89935647,"remaining_time":7.098071003},
{"learn":[2.117494584],"iteration":678,"passed_time":14.92279321,"remaining_time":7.076788534},
{"learn":[2.117006855],"iteration":679,"passed_time":14.96561071,"remaining_time":7.064648584},
{"learn":[2.116341902],"iteration":680,"passed_time":15.02836394,"remaining_time":7.061786286},
{"learn":[2.115694567],"iteration":681,"passed_time":15.09117076,"remaining_time":7.058773422},
{"learn":[2.114709306],"iteration":682,"passed_time":15.13462372,"remaining_time":7.046574442},
{"learn":[2.11418323],"iteration":683,"passed_time":15.15965307,"remaining_time":7.025745649},
{"learn":[2.11358186],"iteration":684,"passed_time":15.2093797,"remaining_time":7.016297787},
{"learn":[2.112762918],"iteration":685,"passed_time":15.23303174,"remaining_time":6.994759471},
{"learn":[2.111781128],"iteration":686,"passed_time":15.25564375,"remaining_time":6.972739647},
{"learn":[2.11118777],"iteration":687,"passed_time":15.27825405,"remaining_time":6.950717323},
{"learn":[2.11038992],"iteration":688,"passed_time":15.29880578,"remaining_time":6.927761107},
{"learn":[2.10989577],"iteration":689,"passed_time":15.31784848,"remaining_time":6.904131705},
{"learn":[2.109385616],"iteration":690,"passed_time":15.34183252,"remaining_time":6.882732391},
{"learn":[2.108582046],"iteration":691,"passed_time":15.36308471,"remaining_time":6.860105746},
{"learn":[2.107880778],"iteration":692,"passed_time":15.38293096,"remaining_time":6.836858206},
{"learn":[2.106926867],"iteration":693,"passed_time":15.4045843,"remaining_time":6.814419855},
{"learn":[2.106406413],"iteration":694,"passed_time":15.42568657,"remaining_time":6.791741138},
{"learn":[2.10573351],"iteration":695,"passed_time":15.44712759,"remaining_time":6.769215396},
{"learn":[2.105174382],"iteration":696,"passed_time":15.46629774,"remaining_time":6.745702314},
{"learn":[2.104441433],"iteration":697,"passed_time":15.48713877,"remaining_time":6.722927002},
{"learn":[2.103774181],"iteration":698,"passed_time":15.50905602,"remaining_time":6.700622199},
{"learn":[2.103244957],"iteration":699,"passed_time":15.52655779,"remaining_time":6.676419849},
{"learn":[2.102638562],"iteration":700,"passed_time":15.54678184,"remaining_time":6.653401645},
{"learn":[2.102133605],"iteration":701,"passed_time":15.56921849,"remaining_time":6.631333801},
{"learn":[2.101459634],"iteration":702,"passed_time":15.58867315,"remaining_time":6.608000852},
{"learn":[2.10075992],"iteration":703,"passed_time":15.60861194,"remaining_time":6.584883164},
{"learn":[2.100268393],"iteration":704,"passed_time":15.62682405,"remaining_time":6.561049532},
{"learn":[2.099752612],"iteration":705,"passed_time":15.64917677,"remaining_time":6.538961963},
{"learn":[2.098985393],"iteration":706,"passed_time":15.67134839,"remaining_time":6.516798342},
{"learn":[2.098149187],"iteration":707,"passed_time":15.68958281,"remaining_time":6.493005314},
{"learn":[2.097624721],"iteration":708,"passed_time":15.70633007,"remaining_time":6.468615486},
{"learn":[2.09694474],"iteration":709,"passed_time":15.72838412,"remaining_time":6.446422222},
{"learn":[2.096183067],"iteration":710,"passed_time":15.74875019,"remaining_time":6.423540865},
{"learn":[2.095440473],"iteration":711,"passed_time":15.7698051,"remaining_time":6.400946173},
{"learn":[2.0948583],"iteration":712,"passed_time":15.78846283,"remaining_time":6.377387509},
{"learn":[2.094322924],"iteration":713,"passed_time":15.80867912,"remaining_time":6.35446906},
{"learn":[2.093112527],"iteration":714,"passed_time":15.82890748,"remaining_time":6.331562992},
{"learn":[2.092116195],"iteration":715,"passed_time":15.8523061,"remaining_time":6.309926312},
{"learn":[2.091228782],"iteration":716,"passed_time":15.87865991,"remaining_time":6.289455251},
{"learn":[2.090275798],"iteration":717,"passed_time":15.89906162,"remaining_time":6.266621779},
{"learn":[2.089654925],"iteration":718,"passed_time":15.92041827,"remaining_time":6.244169614},
{"learn":[2.088686638],"iteration":719,"passed_time":15.94341893,"remaining_time":6.222362111},
{"learn":[2.08820863],"iteration":720,"passed_time":15.96502772,"remaining_time":6.200010765},
{"learn":[2.087811904],"iteration":721,"passed_time":15.98913964,"remaining_time":6.178628752},
{"learn":[2.087155305],"iteration":722,"passed_time":16.01267994,"remaining_time":6.157019395},
{"learn":[2.086146617],"iteration":723,"passed_time":16.03359525,"remaining_time":6.134400393},
{"learn":[2.084669717],"iteration":724,"passed_time":16.05528099,"remaining_time":6.112079382},
{"learn":[2.0838466],"iteration":725,"passed_time":16.07639119,"remaining_time":6.089542118},
{"learn":[2.082669702],"iteration":726,"passed_time":16.09527863,"remaining_time":6.06617104},
{"learn":[2.082123416],"iteration":727,"passed_time":16.11467476,"remaining_time":6.043003035},
{"learn":[2.081178609],"iteration":728,"passed_time":16.14011654,"remaining_time":6.022101096},
{"learn":[2.080420908],"iteration":729,"passed_time":16.16404577,"remaining_time":6.000625211},
{"learn":[2.079623599],"iteration":730,"passed_time":16.18315671,"remaining_time":5.977362945},
{"learn":[2.07884733],"iteration":731,"passed_time":16.20178776,"remaining_time":5.953935664},
{"learn":[2.078061604],"iteration":732,"passed_time":16.22520066,"remaining_time":5.932269817},
{"learn":[2.077505321],"iteration":733,"passed_time":16.25067673,"remaining_time":5.911349709},
{"learn":[2.077038922],"iteration":734,"passed_time":16.27743431,"remaining_time":5.890880987},
{"learn":[2.075930489],"iteration":735,"passed_time":16.2977382,"remaining_time":5.868071497},
{"learn":[2.075350605],"iteration":736,"passed_time":16.31786315,"remaining_time":5.84520471},
{"learn":[2.074700977],"iteration":737,"passed_time":16.34074994,"remaining_time":5.823329587},
{"learn":[2.074308269],"iteration":738,"passed_time":16.36272899,"remaining_time":5.801129897},
{"learn":[2.07356048],"iteration":739,"passed_time":16.38408216,"remaining_time":5.778710059},
{"learn":[2.072623149],"iteration":740,"passed_time":16.40343671,"remaining_time":5.755591829},
{"learn":[2.072035389],"iteration":741,"passed_time":16.42574005,"remaining_time":5.733513036},
{"learn":[2.07121271],"iteration":742,"passed_time":16.44400384,"remaining_time":5.710030944},
{"learn":[2.07027169],"iteration":743,"passed_time":16.46268842,"remaining_time":5.68670823},
{"learn":[2.06978305],"iteration":744,"passed_time":16.48289795,"remaining_time":5.663921981},
{"learn":[2.068953209],"iteration":745,"passed_time":16.50273562,"remaining_time":5.641015526},
{"learn":[2.068186571],"iteration":746,"passed_time":16.52185719,"remaining_time":5.617873797},
{"learn":[2.067242637],"iteration":747,"passed_time":16.54149529,"remaining_time":5.594917524},
{"learn":[2.066822725],"iteration":748,"passed_time":16.55991341,"remaining_time":5.571559653},
{"learn":[2.066371569],"iteration":749,"passed_time":16.57729051,"remaining_time":5.547866556},
{"learn":[2.065571138],"iteration":750,"passed_time":16.59590533,"remaining_time":5.524602308},
{"learn":[2.065082745],"iteration":751,"passed_time":16.61411505,"remaining_time":5.501216288},
{"learn":[2.06393878],"iteration":752,"passed_time":16.63187005,"remaining_time":5.477694254},
{"learn":[2.063154232],"iteration":753,"passed_time":16.65017897,"remaining_time":5.454368972},
{"learn":[2.062347662],"iteration":754,"passed_time":16.66908852,"remaining_time":5.431252682},
{"learn":[2.061789233],"iteration":755,"passed_time":16.68857094,"remaining_time":5.408333174},
{"learn":[2.060869474],"iteration":756,"passed_time":16.71204172,"remaining_time":5.386708297},
{"learn":[2.060417103],"iteration":757,"passed_time":16.73175614,"remaining_time":5.363874331},
{"learn":[2.059871126],"iteration":758,"passed_time":16.75359554,"remaining_time":5.341726116},
{"learn":[2.059231408],"iteration":759,"passed_time":16.77345153,"remaining_time":5.318949761},
{"learn":[2.058544785],"iteration":760,"passed_time":16.79150752,"remaining_time":5.295613411},
{"learn":[2.057955505],"iteration":761,"passed_time":16.81087444,"remaining_time":5.272702087},
{"learn":[2.057153144],"iteration":762,"passed_time":16.83013476,"remaining_time":5.249766805},
{"learn":[2.05634816],"iteration":763,"passed_time":16.85126562,"remaining_time":5.227421403},
{"learn":[2.055647207],"iteration":764,"passed_time":16.86958435,"remaining_time":5.204211643},
{"learn":[2.055103231],"iteration":765,"passed_time":16.88824309,"remaining_time":5.181118965},
{"learn":[2.054446956],"iteration":766,"passed_time":16.90900649,"remaining_time":5.158679945},
{"learn":[2.053658955],"iteration":767,"passed_time":16.93377685,"remaining_time":5.137460945},
{"learn":[2.053052114],"iteration":768,"passed_time":16.95632327,"remaining_time":5.115561767},
{"learn":[2.052715287],"iteration":769,"passed_time":16.97854695,"remaining_time":5.093564086},
{"learn":[2.052321878],"iteration":770,"passed_time":16.99564709,"remaining_time":5.070037394},
{"learn":[2.051686762],"iteration":771,"passed_time":17.01474984,"remaining_time":5.04712139},
{"learn":[2.051229971],"iteration":772,"passed_time":17.03270177,"remaining_time":5.023875814},
{"learn":[2.050768896],"iteration":773,"passed_time":17.0595797,"remaining_time":5.003261747},
{"learn":[2.049859696],"iteration":774,"passed_time":17.07856926,"remaining_time":4.980331165},
{"learn":[2.049053441],"iteration":775,"passed_time":17.098198,"remaining_time":4.957596069},
{"learn":[2.048535429],"iteration":776,"passed_time":17.11725927,"remaining_time":4.934705375},
{"learn":[2.047842627],"iteration":777,"passed_time":17.14006691,"remaining_time":4.912898356},
{"learn":[2.046509845],"iteration":778,"passed_time":17.16100333,"remaining_time":4.890555507},
{"learn":[2.045783343],"iteration":779,"passed_time":17.1805553,"remaining_time":4.867824002},
{"learn":[2.045193443],"iteration":780,"passed_time":17.20984265,"remaining_time":4.847842999},
{"learn":[2.044687439],"iteration":781,"passed_time":17.23420372,"remaining_time":4.826458587},
{"learn":[2.043751078],"iteration":782,"passed_time":17.25681764,"remaining_time":4.804580134},
{"learn":[2.043022706],"iteration":783,"passed_time":17.27937693,"remaining_time":4.782684686},
{"learn":[2.042196573],"iteration":784,"passed_time":17.30611581,"remaining_time":4.761937599},
{"learn":[2.041852892],"iteration":785,"passed_time":17.33433536,"remaining_time":4.741580283},
{"learn":[2.041295736],"iteration":786,"passed_time":17.36924315,"remaining_time":4.723021643},
{"learn":[2.040645965],"iteration":787,"passed_time":17.39669021,"remaining_time":4.702404841},
{"learn":[2.039850102],"iteration":788,"passed_time":17.41965364,"remaining_time":4.680565996},
{"learn":[2.039196518],"iteration":789,"passed_time":17.44141964,"remaining_time":4.658404485},
{"learn":[2.038760352],"iteration":790,"passed_time":17.46413642,"remaining_time":4.636496396},
{"learn":[2.037824516],"iteration":791,"passed_time":17.49068762,"remaining_time":4.615598121},
{"learn":[2.037231801],"iteration":792,"passed_time":17.50855899,"remaining_time":4.592408916},
{"learn":[2.036580248],"iteration":793,"passed_time":17.52878986,"remaining_time":4.569848239},
{"learn":[2.036207202],"iteration":794,"passed_time":17.55002961,"remaining_time":4.547554844},
{"learn":[2.035629527],"iteration":795,"passed_time":17.57546285,"remaining_time":4.526344076},
{"learn":[2.034549795],"iteration":796,"passed_time":17.60043327,"remaining_time":4.505004249},
{"learn":[2.034220504],"iteration":797,"passed_time":17.62068476,"remaining_time":4.482454894},
{"learn":[2.033579088],"iteration":798,"passed_time":17.64045769,"remaining_time":4.459790305},
{"learn":[2.032909633],"iteration":799,"passed_time":17.66369015,"remaining_time":4.438002151},
{"learn":[2.03201925],"iteration":800,"passed_time":17.68865107,"remaining_time":4.416641966},
{"learn":[2.031542448],"iteration":801,"passed_time":17.71289853,"remaining_time":4.395095769},
{"learn":[2.031167478],"iteration":802,"passed_time":17.73458626,"remaining_time":4.372911681},
{"learn":[2.030368658],"iteration":803,"passed_time":17.75339085,"remaining_time":4.350022384},
{"learn":[2.030043503],"iteration":804,"passed_time":17.77273155,"remaining_time":4.327273769},
{"learn":[2.029666125],"iteration":805,"passed_time":17.7955485,"remaining_time":4.305374637},
{"learn":[2.029238716],"iteration":806,"passed_time":17.81345872,"remaining_time":4.282293669},
{"learn":[2.028663646],"iteration":807,"passed_time":17.83325522,"remaining_time":4.259676061},
{"learn":[2.028019727],"iteration":808,"passed_time":17.85160978,"remaining_time":4.236723212},
{"learn":[2.027162962],"iteration":809,"passed_time":17.8703857,"remaining_time":4.213881071},
{"learn":[2.026675848],"iteration":810,"passed_time":17.89329014,"remaining_time":4.192016186},
{"learn":[2.026092754],"iteration":811,"passed_time":17.91445606,"remaining_time":4.169744084},
{"learn":[2.025498907],"iteration":812,"passed_time":17.93419622,"remaining_time":4.147145005},
{"learn":[2.024901297],"iteration":813,"passed_time":17.95351492,"remaining_time":4.124456129},
{"learn":[2.024216876],"iteration":814,"passed_time":17.97615421,"remaining_time":4.102533353},
{"learn":[2.023633877],"iteration":815,"passed_time":18.03323584,"remaining_time":4.08841744},
{"learn":[2.023047451],"iteration":816,"passed_time":18.05553626,"remaining_time":4.066363124},
{"learn":[2.022609726],"iteration":817,"passed_time":18.07784677,"remaining_time":4.044310463},
{"learn":[2.021993421],"iteration":818,"passed_time":18.09823073,"remaining_time":4.021829051},
{"learn":[2.02131206],"iteration":819,"passed_time":18.11893456,"remaining_time":3.999423359},
{"learn":[2.020535035],"iteration":820,"passed_time":18.13955437,"remaining_time":3.977003395},
{"learn":[2.019836519],"iteration":821,"passed_time":18.15984789,"remaining_time":3.954516755},
{"learn":[2.019317789],"iteration":822,"passed_time":18.17857578,"remaining_time":3.931696828},
{"learn":[2.018749256],"iteration":823,"passed_time":18.20241001,"remaining_time":3.909983704},
{"learn":[2.018059628],"iteration":824,"passed_time":18.22251781,"remaining_time":3.887470467},
{"learn":[2.017672985],"iteration":825,"passed_time":18.2416832,"remaining_time":3.86476339},
{"learn":[2.01698887],"iteration":826,"passed_time":18.2658551,"remaining_time":3.843118244},
{"learn":[2.016064462],"iteration":827,"passed_time":18.28524415,"remaining_time":3.820467678},
{"learn":[2.015727234],"iteration":828,"passed_time":18.30786246,"remaining_time":3.798494986},
{"learn":[2.015269965],"iteration":829,"passed_time":18.32693916,"remaining_time":3.77579108},
{"learn":[2.014704023],"iteration":830,"passed_time":18.34805995,"remaining_time":3.753514069},
{"learn":[2.013870537],"iteration":831,"passed_time":18.36595265,"remaining_time":3.730584133},
{"learn":[2.013289112],"iteration":832,"passed_time":18.38742899,"remaining_time":3.708389039},
{"learn":[2.01254733],"iteration":833,"passed_time":18.40635373,"remaining_time":3.685684739},
{"learn":[2.012066606],"iteration":834,"passed_time":18.42847192,"remaining_time":3.663624358},
{"learn":[2.011409823],"iteration":835,"passed_time":18.44812921,"remaining_time":3.641078134},
{"learn":[2.010948965],"iteration":836,"passed_time":18.46762701,"remaining_time":3.618507562},
{"learn":[2.010344272],"iteration":837,"passed_time":18.48604279,"remaining_time":3.59573386},
{"learn":[2.00952052],"iteration":838,"passed_time":18.50553005,"remaining_time":3.573177434},
{"learn":[2.009110962],"iteration":839,"passed_time":18.5238643,"remaining_time":3.550407324},
{"learn":[2.00865335],"iteration":840,"passed_time":18.54376987,"remaining_time":3.527946706},
{"learn":[2.008089662],"iteration":841,"passed_time":18.56318484,"remaining_time":3.505399513},
{"learn":[2.00761743],"iteration":842,"passed_time":18.58346186,"remaining_time":3.483021322},
{"learn":[2.007041033],"iteration":843,"passed_time":18.60157002,"remaining_time":3.46024466},
{"learn":[2.006478114],"iteration":844,"passed_time":18.62073483,"remaining_time":3.437674122},
{"learn":[2.006044885],"iteration":845,"passed_time":18.64595984,"remaining_time":3.416221957},
{"learn":[2.005555282],"iteration":846,"passed_time":18.66527786,"remaining_time":3.393686884},
{"learn":[2.004991988],"iteration":847,"passed_time":18.68471854,"remaining_time":3.371181529},
{"learn":[2.004751307],"iteration":848,"passed_time":18.70363682,"remaining_time":3.348589866},
{"learn":[2.004214845],"iteration":849,"passed_time":18.72538808,"remaining_time":3.326510118},
{"learn":[2.003576599],"iteration":850,"passed_time":18.74440623,"remaining_time":3.303949394},
{"learn":[2.003086432],"iteration":851,"passed_time":18.76319019,"remaining_time":3.28135603},
{"learn":[2.002319661],"iteration":852,"passed_time":18.78287932,"remaining_time":3.258928651},
{"learn":[2.001966073],"iteration":853,"passed_time":18.80048543,"remaining_time":3.236149132},
{"learn":[2.001580578],"iteration":854,"passed_time":18.81967628,"remaining_time":3.213652324},
{"learn":[2.00114082],"iteration":855,"passed_time":18.83863357,"remaining_time":3.191123677},
{"learn":[2.000690286],"iteration":856,"passed_time":18.85577128,"remaining_time":3.168297625},
{"learn":[2.000440869],"iteration":857,"passed_time":18.88502051,"remaining_time":3.147503419},
{"learn":[2.000011295],"iteration":858,"passed_time":18.90163881,"remaining_time":3.124601526},
{"learn":[1.999542816],"iteration":859,"passed_time":18.92036297,"remaining_time":3.102059511},
{"learn":[1.998823613],"iteration":860,"passed_time":18.94216099,"remaining_time":3.080026176},
{"learn":[1.998446225],"iteration":861,"passed_time":19.01353239,"remaining_time":3.065987242},
{"learn":[1.997650653],"iteration":862,"passed_time":19.08717833,"remaining_time":3.052179154},
{"learn":[1.997200923],"iteration":863,"passed_time":19.12708101,"remaining_time":3.032882059},
{"learn":[1.996613065],"iteration":864,"passed_time":19.14563031,"remaining_time":3.010180026},
{"learn":[1.995923129],"iteration":865,"passed_time":19.16375221,"remaining_time":2.987420956},
{"learn":[1.995156543],"iteration":866,"passed_time":19.18243995,"remaining_time":2.964760038},
{"learn":[1.99447762],"iteration":867,"passed_time":19.20176991,"remaining_time":2.94220668},
{"learn":[1.993989458],"iteration":868,"passed_time":19.22062666,"remaining_time":2.91958886},
{"learn":[1.992658517],"iteration":869,"passed_time":19.23894988,"remaining_time":2.896899349},
{"learn":[1.992052612],"iteration":870,"passed_time":19.25764759,"remaining_time":2.874275759},
{"learn":[1.991455158],"iteration":871,"passed_time":19.27581989,"remaining_time":2.851583446},
{"learn":[1.991007064],"iteration":872,"passed_time":19.29401242,"remaining_time":2.828904455},
{"learn":[1.990587968],"iteration":873,"passed_time":19.31319885,"remaining_time":2.806380154},
{"learn":[1.989630753],"iteration":874,"passed_time":19.33432284,"remaining_time":2.784142489},
{"learn":[1.989079125],"iteration":875,"passed_time":19.35593274,"remaining_time":2.761976704},
{"learn":[1.988535787],"iteration":876,"passed_time":19.37726472,"remaining_time":2.739772891},
{"learn":[1.98791127],"iteration":877,"passed_time":19.39766271,"remaining_time":2.71744022},
{"learn":[1.987246876],"iteration":878,"passed_time":19.41665133,"remaining_time":2.694916339},
{"learn":[1.986573177],"iteration":879,"passed_time":19.43530656,"remaining_time":2.672354652},
{"learn":[1.986057717],"iteration":880,"passed_time":19.4544667,"remaining_time":2.649870607},
{"learn":[1.98558072],"iteration":881,"passed_time":19.47302692,"remaining_time":2.627313156},
{"learn":[1.985208636],"iteration":882,"passed_time":19.49055908,"remaining_time":2.604627374},
{"learn":[1.984258158],"iteration":883,"passed_time":19.51435767,"remaining_time":2.582782632},
{"learn":[1.98379413],"iteration":884,"passed_time":19.53261065,"remaining_time":2.560206593},
{"learn":[1.983068863],"iteration":885,"passed_time":19.55263466,"remaining_time":2.537870187},
{"learn":[1.982342685],"iteration":886,"passed_time":19.57370781,"remaining_time":2.515673833},
{"learn":[1.981606542],"iteration":887,"passed_time":19.59144819,"remaining_time":2.493055908},
{"learn":[1.980901234],"iteration":888,"passed_time":19.60996463,"remaining_time":2.470546725},
{"learn":[1.980221603],"iteration":889,"passed_time":19.6292949,"remaining_time":2.448148016},
{"learn":[1.979917276],"iteration":890,"passed_time":19.64750953,"remaining_time":2.425618461},
{"learn":[1.979576398],"iteration":891,"passed_time":19.66491866,"remaining_time":2.40300015},
{"learn":[1.978333136],"iteration":892,"passed_time":19.68367405,"remaining_time":2.380556324},
{"learn":[1.977649528],"iteration":893,"passed_time":19.70574944,"remaining_time":2.35851811},
{"learn":[1.976857111],"iteration":894,"passed_time":19.72852683,"remaining_time":2.336562954},
{"learn":[1.976256821],"iteration":895,"passed_time":19.74672011,"remaining_time":2.314068763},
{"learn":[1.975771858],"iteration":896,"passed_time":19.76341398,"remaining_time":2.291410316},
{"learn":[1.975042747],"iteration":897,"passed_time":19.78292074,"remaining_time":2.269087791},
{"learn":[1.974740316],"iteration":898,"passed_time":19.80162143,"remaining_time":2.246680073},
{"learn":[1.97409008],"iteration":899,"passed_time":19.81980105,"remaining_time":2.224222118},
{"learn":[1.973574108],"iteration":900,"passed_time":19.838863,"remaining_time":2.201871587},
{"learn":[1.972701791],"iteration":901,"passed_time":19.85748123,"remaining_time":2.179479647},
{"learn":[1.971772514],"iteration":902,"passed_time":19.87681929,"remaining_time":2.157174187},
{"learn":[1.970957673],"iteration":903,"passed_time":19.89438288,"remaining_time":2.134684888},
{"learn":[1.970097091],"iteration":904,"passed_time":19.91739632,"remaining_time":2.112784582},
{"learn":[1.969622471],"iteration":905,"passed_time":19.9410122,"remaining_time":2.090944987},
{"learn":[1.969073541],"iteration":906,"passed_time":19.95839174,"remaining_time":2.068455153},
{"learn":[1.968024392],"iteration":907,"passed_time":19.97647753,"remaining_time":2.04604891},
{"learn":[1.967488025],"iteration":908,"passed_time":19.99393908,"remaining_time":2.023588994},
{"learn":[1.966745831],"iteration":909,"passed_time":20.01183138,"remaining_time":2.001183138},
{"learn":[1.965987679],"iteration":910,"passed_time":20.03176315,"remaining_time":1.978988675},
{"learn":[1.965431561],"iteration":911,"passed_time":20.04961639,"remaining_time":1.956596336},
{"learn":[1.964943314],"iteration":912,"passed_time":20.06887268,"remaining_time":1.934349174},
{"learn":[1.964263043],"iteration":913,"passed_time":20.08774414,"remaining_time":1.912071926},
{"learn":[1.963483449],"iteration":914,"passed_time":20.10659935,"remaining_time":1.889800595},
{"learn":[1.962897882],"iteration":915,"passed_time":20.12403158,"remaining_time":1.867404677},
{"learn":[1.962189456],"iteration":916,"passed_time":20.1417198,"remaining_time":1.845043035},
{"learn":[1.961544872],"iteration":917,"passed_time":20.16578449,"remaining_time":1.823268097},
{"learn":[1.960633107],"iteration":918,"passed_time":20.18558118,"remaining_time":1.801107353},
{"learn":[1.959932319],"iteration":919,"passed_time":20.20631137,"remaining_time":1.779033936},
{"learn":[1.959165373],"iteration":920,"passed_time":20.22588893,"remaining_time":1.756863316},
{"learn":[1.958668796],"iteration":921,"passed_time":20.24403513,"remaining_time":1.734575678},
{"learn":[1.95800571],"iteration":922,"passed_time":20.2630694,"remaining_time":1.712372062},
{"learn":[1.957494345],"iteration":923,"passed_time":20.28195247,"remaining_time":1.690162706},
{"learn":[1.957129043],"iteration":924,"passed_time":20.30114919,"remaining_time":1.667986312},
{"learn":[1.956496295],"iteration":925,"passed_time":20.32350648,"remaining_time":1.646072339},
{"learn":[1.955948488],"iteration":926,"passed_time":20.34182518,"remaining_time":1.62383502},
{"learn":[1.954995632],"iteration":927,"passed_time":20.36055202,"remaining_time":1.601638252},
{"learn":[1.954172885],"iteration":928,"passed_time":20.38231351,"remaining_time":1.579684147},
{"learn":[1.953378336],"iteration":929,"passed_time":20.40113768,"remaining_time":1.55750621},
{"learn":[1.952578509],"iteration":930,"passed_time":20.41870188,"remaining_time":1.535240743},
{"learn":[1.951928815],"iteration":931,"passed_time":20.43807256,"remaining_time":1.513119106},
{"learn":[1.950832219],"iteration":932,"passed_time":20.45636502,"remaining_time":1.490924782},
{"learn":[1.950036662],"iteration":933,"passed_time":20.47553498,"remaining_time":1.46880176},
{"learn":[1.949600661],"iteration":934,"passed_time":20.49298343,"remaining_time":1.446563536},
{"learn":[1.94918933],"iteration":935,"passed_time":20.5112179,"remaining_time":1.424390132},
{"learn":[1.948568198],"iteration":936,"passed_time":20.53221141,"remaining_time":1.402413586},
{"learn":[1.947929315],"iteration":937,"passed_time":20.55130186,"remaining_time":1.380311319},
{"learn":[1.947509756],"iteration":938,"passed_time":20.56914216,"remaining_time":1.358132922},
{"learn":[1.946761582],"iteration":939,"passed_time":20.58803919,"remaining_time":1.336032331},
{"learn":[1.946214456],"iteration":940,"passed_time":20.60875284,"remaining_time":1.314054379},
{"learn":[1.945180293],"iteration":941,"passed_time":20.62764693,"remaining_time":1.291965148},
{"learn":[1.94438244],"iteration":942,"passed_time":20.64633919,"remaining_time":1.269870279},
{"learn":[1.943752278],"iteration":943,"passed_time":20.66493032,"remaining_time":1.247776513},
{"learn":[1.943346955],"iteration":944,"passed_time":20.68191903,"remaining_time":1.225595202},
{"learn":[1.94267715],"iteration":945,"passed_time":20.69954567,"remaining_time":1.203461957},
{"learn":[1.942216304],"iteration":946,"passed_time":20.72542841,"remaining_time":1.181809012},
{"learn":[1.941476339],"iteration":947,"passed_time":20.74369953,"remaining_time":1.159721598},
{"learn":[1.940624374],"iteration":948,"passed_time":20.76229002,"remaining_time":1.137659727},
{"learn":[1.939763604],"iteration":949,"passed_time":20.78010268,"remaining_time":1.115563407},
{"learn":[1.939072895],"iteration":950,"passed_time":20.7980352,"remaining_time":1.093482397},
{"learn":[1.938498166],"iteration":951,"passed_time":20.81962255,"remaining_time":1.071598219},
{"learn":[1.93784977],"iteration":952,"passed_time":20.8423231,"remaining_time":1.049770733},
{"learn":[1.937465906],"iteration":953,"passed_time":20.86595039,"remaining_time":1.027987074},
{"learn":[1.93667589],"iteration":954,"passed_time":20.89782665,"remaining_time":1.006596886},
{"learn":[1.9359579],"iteration":955,"passed_time":20.92552771,"remaining_time":0.9849882292},
{"learn":[1.935185051],"iteration":956,"passed_time":20.94997959,"remaining_time":0.9632174526},
{"learn":[1.934830475],"iteration":957,"passed_time":20.97169721,"remaining_time":0.9413183506},
{"learn":[1.934222432],"iteration":958,"passed_time":20.99424598,"remaining_time":0.9194560285},
{"learn":[1.933769143],"iteration":959,"passed_time":21.01738306,"remaining_time":0.8976174015},
{"learn":[1.932627824],"iteration":960,"passed_time":21.0371851,"remaining_time":0.8756372572},
{"learn":[1.932222902],"iteration":961,"passed_time":21.06258492,"remaining_time":0.8538885779},
{"learn":[1.931526337],"iteration":962,"passed_time":21.0808364,"remaining_time":0.831850242},
{"learn":[1.930761355],"iteration":963,"passed_time":21.10156602,"remaining_time":0.8099148783},
{"learn":[1.930163927],"iteration":964,"passed_time":21.12669937,"remaining_time":0.7881462976},
{"learn":[1.929341011],"iteration":965,"passed_time":21.14554381,"remaining_time":0.7661428916},
{"learn":[1.92866955],"iteration":966,"passed_time":21.16943302,"remaining_time":0.7443233947},
{"learn":[1.927886555],"iteration":967,"passed_time":21.19937316,"remaining_time":0.7227059033},
{"learn":[1.927513013],"iteration":968,"passed_time":21.24990312,"remaining_time":0.7017511868},
{"learn":[1.926984778],"iteration":969,"passed_time":21.2796067,"remaining_time":0.6800699049},
{"learn":[1.926765925],"iteration":970,"passed_time":21.30922313,"remaining_time":0.6583694066},
{"learn":[1.926227341],"iteration":971,"passed_time":21.33690195,"remaining_time":0.6365948114},
{"learn":[1.925992927],"iteration":972,"passed_time":21.36240254,"remaining_time":0.6147453969},
{"learn":[1.92529775],"iteration":973,"passed_time":21.38470703,"remaining_time":0.592799887},
{"learn":[1.924750203],"iteration":974,"passed_time":21.40853338,"remaining_time":0.5708942236},
{"learn":[1.924125162],"iteration":975,"passed_time":21.42904385,"remaining_time":0.5488996887},
{"learn":[1.923723092],"iteration":976,"passed_time":21.45112035,"remaining_time":0.5269466616},
{"learn":[1.923325582],"iteration":977,"passed_time":21.48912278,"remaining_time":0.5053679181},
{"learn":[1.922714733],"iteration":978,"passed_time":21.51273877,"remaining_time":0.4834323319},
{"learn":[1.922326788],"iteration":979,"passed_time":21.53505578,"remaining_time":0.461465481},
{"learn":[1.921940794],"iteration":980,"passed_time":21.55538242,"remaining_time":0.4394573378},
{"learn":[1.921021502],"iteration":981,"passed_time":21.57486128,"remaining_time":0.4174362161},
{"learn":[1.920584943],"iteration":982,"passed_time":21.59715995,"remaining_time":0.3954719014},
{"learn":[1.919918402],"iteration":983,"passed_time":21.61932248,"remaining_time":0.373504555},
{"learn":[1.919136897],"iteration":984,"passed_time":21.64228511,"remaining_time":0.351549809},
{"learn":[1.918280666],"iteration":985,"passed_time":21.66883605,"remaining_time":0.3296476072},
{"learn":[1.917705132],"iteration":986,"passed_time":21.69006526,"remaining_time":0.3076605001},
{"learn":[1.917198725],"iteration":987,"passed_time":21.71282032,"remaining_time":0.2856950042},
{"learn":[1.916549299],"iteration":988,"passed_time":21.73592837,"remaining_time":0.2637321945},
{"learn":[1.915652916],"iteration":989,"passed_time":21.75616269,"remaining_time":0.241735141},
{"learn":[1.914938993],"iteration":990,"passed_time":21.7761541,"remaining_time":0.2197391937},
{"learn":[1.91439512],"iteration":991,"passed_time":21.7969137,"remaining_time":0.1977542574},
{"learn":[1.914030606],"iteration":992,"passed_time":21.81735598,"remaining_time":0.1757692325},
{"learn":[1.913664593],"iteration":993,"passed_time":21.83731608,"remaining_time":0.1537839161},
{"learn":[1.91336569],"iteration":994,"passed_time":21.85810342,"remaining_time":0.1318076588},
{"learn":[1.912828849],"iteration":995,"passed_time":21.88159113,"remaining_time":0.109847345},
{"learn":[1.912396746],"iteration":996,"passed_time":21.90739544,"remaining_time":0.08789326153},
{"learn":[1.911803193],"iteration":997,"passed_time":21.94234735,"remaining_time":0.06595895996},
{"learn":[1.91114868],"iteration":998,"passed_time":21.96598034,"remaining_time":0.04397593662},
{"learn":[1.910618853],"iteration":999,"passed_time":21.99096782,"remaining_time":0.02199096782},
{"learn":[1.91014499],"iteration":1000,"passed_time":22.01309587,"remaining_time":0}
]}